Workbook
Name __k10003: [3]L100100!#REF!
Name _121_201_103: #REF!
Name _121_201_103: #REF!
Name _ABR1: [4]ABR!$A$3:$K$598
Name _ABR2: [4]ABR!$A$603:$N$612
Name _ABR3: [4]ABR!$A$617:$O$637
Name _AGO1: [4]AGO!$A$3:$K$719
Name _AGO2: [4]AGO!$A$724:$N$735
Name _AGO3: [4]AGO!$A$740:$O$791
Name _CUM1: #REF!
Name _CUM2: #REF!
Name _CUM3: #REF!
Name _CUM4: #REF!
Name _CUM5: #REF!
Name _CUM6: #REF!
Name _DEZ1: [4]DEZ!$A$3:$K$5
Name _DEZ2: [4]DEZ!$A$10:$N$12
Name _DEZ3: [4]DEZ!$A$17:$O$19
Name _FEB99: [5]PLANILHA!$A$3:$GC$12
Name _FEV1: [4]FEV!$A$3:$K$447
Name _FEV2: [4]FEV!$A$452:$N$460
Name _FEV3: [4]FEV!$A$465:$O$476
Name _JAN1: [4]JAN!$A$3:$K$434
Name _JAN2: [4]JAN!$A$439:$N$449
Name _JAN3: [4]JAN!$A$454:$O$466
Name _JUL1: [4]JUL!$A$3:$K$522
Name _JUL2: [4]JUL!$A$527:$N$537
Name _JUL3: [4]JUL!$A$542:$O$565
Name _JUN1: [4]JUN!$A$3:$K$532
Name _JUN2: [4]JUN!$A$537:$N$548
Name _JUN3: [4]JUN!$A$554:$O$581
Name _k10003: [6]L100100!#REF!
Name _MAI1: [4]MAI!$A$3:$K$495
Name _MAI2: [4]MAI!$A$500:$N$509
Name _MAI3: [4]MAI!$A$514:$O$523
Name _MAR1: [4]MAR!$A$3:$K$672
Name _MAR2: [4]MAR!$A$677:$N$680
Name _MAR3: [4]MAR!$A$685:$O$698
Name _NOV1: [4]NOV!$A$3:$K$5
Name _NOV2: [4]NOV!$A$10:$N$12
Name _NOV3: [4]NOV!$A$17:$O$19
Name _OBS1: Capa!$B$22
Name _OBS1: #REF!
Name _OBS2: Capa!#REF!
Name _OBS2: #REF!
Name _OBS3: Capa!#REF!
Name _OBS3: #REF!
Name _OBS4: Capa!$B$23
Name _OBS4: #REF!
Name _OBS5: Capa!$B$24
Name _OBS5: #REF!
Name _OBS6: Capa!$B$25
Name _OBS6: #REF!
Name _OUT1: [4]OUT!$A$3:$K$5
Name _OUT2: [4]OUT!$A$10:$N$12
Name _OUT3: [4]OUT!$A$17:$O$19
Name _PL1: #REF!
Name _PRT1: [4]VOUCHER!$V$32
Name _PRT10: [4]VOUCHER!$V$356
Name _PRT11: [4]VOUCHER!$V$392

Sheet Parametros
A1: Pergunta 01 : Da Conta ? | B1: 21510050
A2: Pergunta 02 : Ate Conta ? | B2: 21510050
A3: Pergunta 03 : Da Data ? | B3: 01/01/2010
A4: Pergunta 04 : Ate a Data ? | B4: 30/06/2026
A5: Pergunta 05 : Moeda ? | B5: 01
A6: Pergunta 06 : Tipo de Saldo ? | B6: 1
A7: Pergunta 07 : Cod. Config. Livros ?
A8: Pergunta 08 : Tipo Relatorio ? | B8: Analitico
A9: Pergunta 09 : Impr. Cta S/ Movim ? | B9: Nao
A10: Pergunta 10 : Junta C.C. Contabil ? | B10: Nao
A11: Pergunta 11 : Impr Cod Conta ? | B11: Normal
A12: Pergunta 12 : Imprime C.C. Extra ? | B12: Sim
A13: Pergunta 13 : Do Centro de Custo ?
A14: Pergunta 14 : Ate Centro de Custo ? | B14: ZZZZZZZZZ
A15: Pergunta 15 : Imprime Item Contab ? | B15: Nao
A16: Pergunta 16 : Do Item Contabil ?
A17: Pergunta 17 : Ate Item Contabil ? | B17: ZZZZZZZZZ
A18: Pergunta 18 : Imprime Classe Vlr ? | B18: Nao
A19: Pergunta 19 : Da Classe de Valor ?
A20: Pergunta 20 : Ate Classe de Valor ? | B20: ZZZZZZZZZ
A21: Pergunta 21 : Salta Folha por Cta ? | B21: Nao
A22: Pergunta 22 : Folha Inicial ? | B22: 1
A23: Pergunta 23 : Folha Final ? | B23: 999999
A24: Pergunta 24 : Folha ao Reiniciar ? | B24: 1
A25: Pergunta 25 : Impr Cod C.Custo ? | B25: Normal
A26: Pergunta 26 : Impr Cod Item ? | B26: Normal
A27: Pergunta 27 : Impr Cod Cl.Valor ? | B27: Normal
A28: Pergunta 28 : Imprime Total Geral ? | B28: Sim
A29: Pergunta 29 : Imprime ? | B29: So Livro
A30: Pergunta 30 : Imprime Valor 0,00 ? | B30: Sim
A31: Pergunta 31 : Salta linha entre contas ? | B31: Nao
A32: Pergunta 32 : Num.linhas p/ o Razao ? | B32: 90
A33: Pergunta 33 : Sld.Ant.Nivel ? | B33: Conta
A34: Pergunta 34 : Descrição na Moeda ? | B34: 01
A35: Pergunta 35 : Cons.Tamanho Total das Entid ? | B35: Sim
A36: Pergunta 36 : Seleciona Filiais ? | B36: Sim
A37: Pergunta 37 : Imprimir Cabeçalho ? | B37: Sim
A38: Pergunta 38 : Filtro de Entidades ? | B38: De/Até
A39: Pergunta 39 : Range de Conta ?
A40: Pergunta 40 : Range de Centro de Custo ?
A41: Pergunta 41 : Range de Item Contabil ?
A42: Pergunta 42 : Range de Classe de Valor ?

Sheet 01.Razão (2)
L2: 225387.67
M5: =SUBTOTAL(9,M7:M120) -> -329237.8
B6: Período | C6: Conta | D6: Conta + Descrição | E6: Data | F6: LOTE/SUB/DOC/LINHA | G6: HISTORICO | H6: C/PARTIDA | I6: FL | J6: C CUSTO | K6: DEBITO | L6: CREDITO | M6: Valor | N6: Obs.
B7: 2021 | C7: =MID(D7,1,12) -> 2.1.1.05.000 | D7: 2.1.1.05.0005 - PROVISAO BONUS A PAGAR | E7: 44316 | F7: 000001001000012001 | G7: PROVISAO DE BONUS MES MARÇO E ABRIL | H7: 4.1.1.01.0026 | I7: 0301 | K7: 0 | L7: 40500 | M7: -40500 | N7: Efeito zero
B8: 2021 | C8: =MID(D8,1,12) -> 2.1.1.05.000 | D8: 2.1.1.05.0005 - PROVISAO BONUS A PAGAR | E8: 44347 | F8: 001010001000001001 | G8: PROVISAO DE BONUS MES MAIO-21 | H8: 4.1.1.01.0026 | I8: 0301 | K8: 0 | L8: 27000 | M8: -27000 | N8: Efeito zero
B9: 2021 | C9: =MID(D9,1,12) -> 2.1.1.05.000 | D9: 2.1.1.05.0005 - PROVISAO BONUS A PAGAR | E9: 44377 | F9: 000001001000001005 | G9: PROVISAO DE BONUS JUN 2021 | H9: 4.1.1.01.0026 | I9: 0301 | K9: 0 | L9: 27000 | M9: -27000 | N9: Efeito zero
B10: 2021 | C10: =MID(D10,1,12) -> 2.1.1.05.000 | D10: 2.1.1.05.0005 - PROVISAO BONUS A PAGAR | E10: 44407 | F10: 000001001000008001 | G10: PROV PROVISAO DE BONUS | H10: 4.1.1.01.0026 | I10: 0301 | K10: 0 | L10: 27000 | M10: -27000 | N10: Efeito zero
B11: 2021 | C11: =MID(D11,1,12) -> 2.1.1.05.000 | D11: 2.1.1.05.0005 - PROVISAO BONUS A PAGAR | E11: 44439 | F11: 000001001000001001 | G11: PROV PROVISAO DE BONUS | H11: 4.1.1.01.0026 | I11: 0301 | K11: 0 | L11: 27000 | M11: -27000 | N11: Efeito zero
B12: 2021 | C12: =MID(D12,1,12) -> 2.1.1.05.000 | D12: 2.1.1.05.0005 - PROVISAO BONUS A PAGAR | E12: 44467 | F12: 000001001000005001 | G12: PROV PROVISAO DE BONUS | H12: 4.1.1.01.0026 | I12: 0301 | K12: 0 | L12: 27000 | M12: -27000 | N12: Efeito zero
B13: 2021 | C13: =MID(D13,1,12) -> 2.1.1.05.000 | D13: 2.1.1.05.0005 - PROVISAO BONUS A PAGAR | E13: 44498 | F13: 000001001000002001 | G13: PROV PROVISAO DE BONUS | H13: 4.1.1.01.0026 | I13: 0301 | K13: 0 | L13: 27000 | M13: -27000 | N13: Efeito zero
B14: 2021 | C14: =MID(D14,1,12) -> 2.1.1.05.000 | D14: 2.1.1.05.0005 - PROVISAO BONUS A PAGAR | E14: 44529 | F14: 000001001000002001 | G14: PROV PROVISAO DE BONUS | H14: 4.1.1.01.0026 | I14: 0301 | K14: 0 | L14: 27000 | M14: -27000 | N14: Efeito zero
B15: 2021 | C15: =MID(D15,1,12) -> 2.1.1.05.000 | D15: 2.1.1.05.0005 - PROVISAO BONUS A PAGAR | E15: 44560 | F15: 000001001000002001 | G15: PROV PROVISAO DE BONUS | H15: 4.1.1.01.0026 | I15: 0301 | K15: 0 | L15: 27000 | M15: -27000 | N15: Efeito zero
B16: 2021 | C16: 2.1.1.05.0005 | D16: 2.1.1.05.0005 - PROVISAO BONUS A PAGAR | E16: 44227 | F16: 000001001000014001 | G16: PROV BONUS A PAGAR ACIONISTA | H16: 4.1.1.01.0026 | I16: 0301 | K16: 0 | L16: 22500 | M16: -22500 | N16: Efeito zero
B17: 2021 | C17: =MID(D17,1,12) -> 2.1.1.05.000 | D17: 2.1.1.05.0005 - PROVISAO BONUS A PAGAR | E17: 44255 | F17: 000001001000001001 | G17: PROV BONUS A PAGAR ACIONISTA | H17: 4.1.1.01.0026 | I17: 0301 | K17: 0 | L17: 22500 | M17: -22500 | N17: Efeito zero
B18: 2021 | C18: =MID(D18,1,12) -> 2.1.1.05.000 | D18: 2.1.1.05.0005 - PROVISAO BONUS A PAGAR | E18: 44286 | F18: 000001001000014001 | G18: PROV BONUS A PAGAR ACIONISTA | H18: 4.1.1.01.0026 | I18: 0301 | K18: 0 | L18: 22500 | M18: -22500 | N18: Efeito zero
B19: 2023 | C19: =MID(D19,1,12) -> 2.1.1.05.000 | D19: 2.1.1.05.0005 - PROVISAO BONUS A PAGAR | E19: 45016 | F19: 000001001000016001 | G19: PROV BONUS | H19: 4.1.1.01.0026 | I19: 0301 | K19: 0 | L19: 1 | M19: =L19*-1 -> -1
B20: 2024 | C20: =MID(D20,1,12) -> 2.1.1.05.000 | D20: 2.1.1.05.0005 - PROVISAO BONUS A PAGAR | E20: 45412 | F20: 000001001000012001 | G20: VLR AJUSTE PROVISAO FILIAL | H20: 4.1.1.01.0026 | I20: 0301 | J20: 0.3.8.000018 | K20: 639.42 | L20: 0 | M20: 639.42 | N20: Efeito zero
B21: 2024 | C21: =MID(D21,1,12) -> 2.1.1.05.000 | D21: 2.1.1.05.0005 - PROVISAO BONUS A PAGAR | E21: 45412 | F21: 000001001000009001 | G21: VLR AJUSTE PROVISAO FILIAL | H21: 4.1.1.01.0026 | I21: 0302 | J21: 0.3.7.000007 | K21: 0 | L21: 639.42 | M21: =L21*-1 -> -639.42 | N21: Efeito zero
B22: 2025 | C22: =MID(D22,1,12) -> 2.1.1.05.000 | D22: 2.1.1.05.0005 - PROVISAO BONUS A PAGAR | E22: 45809 | F22: 000001001000007001 | G22: PROVISÃO BONUS-JUN/25 | H22: 4.1.1.01.0026 | I22: 0301 | K22: 0 | L22: 1408 | M22: =L22*-1 -> -1408
B23: 2026 | C23: =MID(D23,1,12) -> 2.1.1.05.000 | D23: 2.1.1.05.0005 - PROVISAO BONUS A PAGAR | E23: 46203 | F23: WN2026001000004004 | G23: RECLAS.VLR FOPG 402 - DESCONTO DIVERSOS | H23: 4.4.1.01.0011 | I23: 0302 | J23: 0.3.2.000001 | K23: 0 | L23: 4159.93 | M23: =L23*-1 -> -4159.93
B24: 2026 | C24: =MID(D24,1,12) -> 2.1.1.05.000 | D24: 2.1.1.05.0005 - PROVISAO BONUS A PAGAR | E24: 46142 | F24: WN2026001000004006 | G24: REV.VLR FOPG 313 - PREMIO | H24: 3.1.1.04.0020 | I24: 0302 | J24: 0.3.7.000007 | K24: 4427.88 | L24: 0 | M24: 4427.88
B25: 2026 | C25: =MID(D25,1,12) -> 2.1.1.05.000 | D25: 2.1.1.05.0005 - PROVISAO BONUS A PAGAR | E25: 46203 | F25: WN2026001000004001 | G25: RECLAS.VLR FOPG 313 - PREMIO | H25: 3.1.1.04.0020 | I25: 0302 | J25: 0.3.8.000025 | K25: 5737.83 | L25: 0 | M25: 5737.83
B26: 2026 | C26: =MID(D26,1,12) -> 2.1.1.05.000 | D26: 2.1.1.05.0005 - PROVISAO BONUS A PAGAR | E26: 46142 | F26: WN2026001000004001 | G26: REV.VLR FOPG 402 - DESCONTO DIVERSOS | H26: 4.4.1.01.0011 | I26: 0302 | K26: 0 | L26: 6111.41 | M26: =L26*-1 -> -6111.41
B27: 2026 | C27: =MID(D27,1,12) -> 2.1.1.05.000 | D27: 2.1.1.05.0005 - PROVISAO BONUS A PAGAR | E27: 46142 | F27: WN2026001000004005 | G27: REV.VLR FOPG 313 - PREMIO | H27: 3.1.1.04.0020 | I27: 0302 | K27: 7176.11 | L27: 0 | M27: 7176.11
B28: 2023 | C28: =MID(D28,1,12) -> 2.1.1.05.000 | D28: 2.1.1.05.0005 - PROVISAO BONUS A PAGAR | E28: 45107 | F28: 000001001000007002 | G28: VLR PROVISAO BONUS | H28: 4.1.1.01.0026 | I28: 0301 | K28: 0 | L28: 7639 | M28: =L28*-1 -> -7639
B29: 2022 | C29: =MID(D29,1,12) -> 2.1.1.05.000 | D29: 2.1.1.05.0005 - PROVISAO BONUS A PAGAR | E29: 44621 | F29: 000001001000007001 | G29: VLR FOL 280220222 EDUARDO DE SETTIALVES | H29: 2.1.1.01.0002 | I29: 0301 | K29: 0 | L29: 8000 | M29: =L29*-1 -> -8000 | N29: Efeito zero
B30: 2022 | C30: =MID(D30,1,12) -> 2.1.1.05.000 | D30: 2.1.1.05.0005 - PROVISAO BONUS A PAGAR | E30: 44624 | F30: 008850001000019003 | G30: VLR PG FOL 280220222- EDUARDO DE SETTIALVES PRO - LABORE | H30: 1.1.1.02.0010 | I30: 0301 | K30: 8000 | L30: 0 | M30: 8000 | N30: Efeito zero
B31: 2022 | C31: =MID(D31,1,12) -> 2.1.1.05.000 | D31: 2.1.1.05.0005 - PROVISAO BONUS A PAGAR | E31: 44651 | F31: 008850001000015001 | G31: VLR FOL 310320222 EDUARDO DE SETTIALVES | H31: 4.1.1.01.0002 | I31: 0301 | K31: 0 | L31: 8000 | M31: =L31*-1 -> -8000 | N31: Efeito zero
B32: 2026 | C32: =MID(D32,1,12) -> 2.1.1.05.000 | D32: 2.1.1.05.0005 - PROVISAO BONUS A PAGAR | E32: 46142 | F32: WN2026001000004002 | G32: REV.VLR FOPG 402 - DESCONTO DIVERSOS | H32: 4.4.1.01.0011 | I32: 0302 | K32: 0 | L32: 8769.49 | M32: =L32*-1 -> -8769.49
B33: 2024 | C33: =MID(D33,1,12) -> 2.1.1.05.000 | D33: 2.1.1.05.0005 - PROVISAO BONUS A PAGAR | E33: 45626 | F33: 000001001000002002 | G33: VLR PROVISAO DE BONUS | H33: 4.1.1.01.0026 | I33: 0301 | K33: 0 | L33: 10257 | M33: =L33*-1 -> -10257
B34: 2024 | C34: =MID(D34,1,12) -> 2.1.1.05.000 | D34: 2.1.1.05.0005 - PROVISAO BONUS A PAGAR | E34: 45657 | F34: 99999L001000001001 | G34: PROVISÃO BONUS | H34: 4.1.1.01.0026 | I34: 0301 | K34: 0 | L34: 10257 | M34: =L34*-1 -> -10257
B35: 2024 | C35: =MID(D35,1,12) -> 2.1.1.05.000 | D35: 2.1.1.05.0005 - PROVISAO BONUS A PAGAR | E35: 45566 | F35: 000001001000001002 | G35: VLR PROVISAO DE BONUS | H35: 4.1.1.01.0026 | I35: 0301 | K35: 0 | L35: 11967 | M35: =L35*-1 -> -11967
B36: 2024 | C36: =MID(D36,1,12) -> 2.1.1.05.000 | D36: 2.1.1.05.0005 - PROVISAO BONUS A PAGAR | E36: 45626 | F36: 000001001000001001 | G36: VLR PREVISAO BONUS | H36: 4.1.1.01.0026 | I36: 0302 | K36: 0 | L36: 12740 | M36: =L36*-1 -> -12740
B37: 2024 | C37: =MID(D37,1,12) -> 2.1.1.05.000 | D37: 2.1.1.05.0005 - PROVISAO BONUS A PAGAR | E37: 45657 | F37: 000001001000008001 | G37: VLR PREVISAO BONUS | H37: 4.1.1.01.0026 | I37: 0302 | K37: 0 | L37: 12740 | M37: =L37*-1 -> -12740
B38: 2024 | C38: =MID(D38,1,12) -> 2.1.1.05.000 | D38: 2.1.1.05.0005 - PROVISAO BONUS A PAGAR | E38: 45412 | F38: 000001001000007003 | G38: 313 - PRÊMIO | H38: 3.1.1.04.0020 | I38: 0302 | K38: 13393.18 | L38: 0 | M38: 13393.18
B39: 2023 | C39: =MID(D39,1,12) -> 2.1.1.05.000 | D39: 2.1.1.05.0005 - PROVISAO BONUS A PAGAR | E39: 45291 | F39: 000001001000006002 | G39: VLR PROVISAO BONUS | H39: 4.1.1.01.0026 | I39: 0301 | K39: 14960 | L39: 0 | M39: 14960
B40: 2024 | C40: =MID(D40,1,12) -> 2.1.1.05.000 | D40: 2.1.1.05.0005 - PROVISAO BONUS A PAGAR | E40: 45412 | F40: 000001001000015001 | G40: VLR PROV BONUS REF 2023 | H40: 4.1.1.01.0026 | I40: 0301 | J40: 0.3.3.000004 | K40: 0 | L40: 17988.02 | M40: =L40*-1 -> -17988.02
B41: 2024 | C41: =MID(D41,1,12) -> 2.1.1.05.000 | D41: 2.1.1.05.0005 - PROVISAO BONUS A PAGAR | E41: 45412 | F41: 000001001000007006 | G41: 313 - PRÊMIO | H41: 4.2.1.01.0020 | I41: 0302 | J41: 0.3.5.000004 | K41: 18052.65 | L41: 0 | M41: 18052.65
B42: 2026 | C42: =MID(D42,1,12) -> 2.1.1.05.000 | D42: 2.1.1.05.0005 - PROVISAO BONUS A PAGAR | E42: 46142 | F42: WN2026001000004003 | G42: REV.VLR FOPG 402 - DESCONTO DIVERSOS | H42: 4.4.1.01.0011 | I42: 0302 | K42: 0 | L42: 20828.18 | M42: =L42*-1 -> -20828.18
B43: 2026 | C43: =MID(D43,1,12) -> 2.1.1.05.000 | D43: 2.1.1.05.0005 - PROVISAO BONUS A PAGAR | E43: 46173 | F43: WN2026001000003003 | G43: REV.VLR FOPG 402 - DESCONTO DIVERSOS | H43: 4.4.1.01.0011 | I43: 0302 | J43: 0.3.2.000001 | K43: 0 | L43: 20828.18 | M43: =L43*-1 -> -20828.18
B44: 2024 | C44: =MID(D44,1,12) -> 2.1.1.05.000 | D44: 2.1.1.05.0005 - PROVISAO BONUS A PAGAR | E44: 45412 | F44: 000001001000014002 | G44: 313 - PREMIO | H44: 4.1.1.01.0020 | I44: 0301 | K44: 21166.53 | L44: 0 | M44: 21166.53
B45: 2026 | C45: =MID(D45,1,12) -> 2.1.1.05.000 | D45: 2.1.1.05.0005 - PROVISAO BONUS A PAGAR | E45: 46053 | F45: 000001001000003001 | G45: PROVISÃO BÔNUS JAN-2026 | H45: 4.1.1.01.0026 | I45: 0302 | K45: 0 | L45: 22757 | M45: =L45*-1 -> -22757
B46: 2026 | C46: =MID(D46,1,12) -> 2.1.1.05.000 | D46: 2.1.1.05.0005 - PROVISAO BONUS A PAGAR | E46: 46081 | F46: 000001001000002001 | G46: PROVISÃO BÔNUS FEV-2026 | H46: 4.1.1.01.0026 | I46: 0302 | K46: 0 | L46: 22757 | M46: =L46*-1 -> -22757
B47: 2026 | C47: =MID(D47,1,12) -> 2.1.1.05.000 | D47: 2.1.1.05.0005 - PROVISAO BONUS A PAGAR | E47: 46112 | F47: 000001001000005001 | G47: PROVISÃO BÔNUS MAR-2026 | H47: 4.1.1.01.0026 | I47: 0302 | K47: 0 | L47: 22757 | M47: =L47*-1 -> -22757
B48: 2026 | C48: =MID(D48,1,12) -> 2.1.1.05.000 | D48: 2.1.1.05.0005 - PROVISAO BONUS A PAGAR | E48: 46142 | F48: 000001001000002001 | G48: PROVISÃO BÔNUS ABR - 2026 | H48: 4.1.1.01.0026 | I48: 0302 | K48: 0 | L48: 22757 | M48: =L48*-1 -> -22757
B49: 2026 | C49: =MID(D49,1,12) -> 2.1.1.05.000 | D49: 2.1.1.05.0005 - PROVISAO BONUS A PAGAR | E49: 46173 | F49: 000001001000002001 | G49: PROVISÃO BÔNUS MAI - 2026 | H49: 4.1.1.01.0026 | I49: 0302 | J49: 0.3.2.000001 | K49: 0 | L49: 22757 | M49: =L49*-1 -> -22757
B50: 2026 | C50: =MID(D50,1,12) -> 2.1.1.05.000 | D50: 2.1.1.05.0005 - PROVISAO BONUS A PAGAR | E50: 46203 | F50: IS0000001000003001 | G50: PROVISÃO BÔNUS JUN-2026 | H50: 4.1.1.01.0026 | I50: 0302 | J50: 0.3.7.000007 | K50: 0 | L50: 22757 | M50: =L50*-1 -> -22757
B51: 2024 | C51: =MID(D51,1,12) -> 2.1.1.05.000 | D51: 2.1.1.05.0005 - PROVISAO BONUS A PAGAR | E51: 45412 | F51: 000001001000007004 | G51: 313 - PRÊMIO | H51: 3.1.1.04.0020 | I51: 0302 | K51: 22791.79 | L51: 0 | M51: 22791.79
B52: 2024 | C52: =MID(D52,1,12) -> 2.1.1.05.000 | D52: 2.1.1.05.0005 - PROVISAO BONUS A PAGAR | E52: 45412 | F52: 000001001000014001 | G52: 313 - PREMIO | H52: 4.2.1.01.0020 | I52: 0301 | J52: 0.3.7.000002 | K52: 23427.51 | L52: 0 | M52: 23427.51
B53: 2024 | C53: =MID(D53,1,12) -> 2.1.1.05.000 | D53: 2.1.1.05.0005 - PROVISAO BONUS A PAGAR | E53: 45412 | F53: 000001001000007005 | G53: 313 - PRÊMIO | H53: 3.1.1.02.0020 | I53: 0302 | J53: 0.1.1.000001 | K53: 24529.8 | L53: 0 | M53: 24529.8 | N53: 341456.04 | O53: 350000 | P53: =N53-O53 -> -8543.96
B54: 2024 | C54: =MID(D54,1,12) -> 2.1.1.05.000 | D54: 2.1.1.05.0005 - PROVISAO BONUS A PAGAR | E54: 45536 | F54: 000001001000002001 | G54: VLR PROVISAO BONUS | H54: 4.1.1.01.0026 | I54: 0302 | K54: 24648 | L54: 0 | M54: 24648 | N54: 284951.33 | O54: 350000 | P54: =N54-O54 -> -65048.67
B55: 2024 | C55: =MID(D55,1,12) -> 2.1.1.05.000 | D55: 2.1.1.05.0005 - PROVISAO BONUS A PAGAR | E55: 45412 | F55: 000001001000014003 | G55: 313 - PREMIO | H55: 3.1.1.04.0020 | I55: 0301 | K55: 25240.72 | L55: 0 | M55: 25240.72
B56: 2026 | C56: =MID(D56,1,12) -> 2.1.1.05.000 | D56: 2.1.1.05.0005 - PROVISAO BONUS A PAGAR | E56: 46173 | F56: WN2026001000003004 | G56: REV.VLR FOPG 313 - PREMIO | H56: 4.1.1.01.0020 | I56: 0302 | J56: 0.3.2.000001 | K56: 27244.78 | L56: 0 | M56: 27244.78
B57: 2024 | C57: =MID(D57,1,12) -> 2.1.1.05.000 | D57: 2.1.1.05.0005 - PROVISAO BONUS A PAGAR | E57: 45412 | F57: 000001001000014004 | G57: 313 - PREMIO | H57: 4.2.1.01.0020 | I57: 0301 | K57: 27273.52 | L57: 0 | M57: 27273.52
B58: 2024 | C58: =MID(D58,1,12) -> 2.1.1.05.000 | D58: 2.1.1.05.0005 - PROVISAO BONUS A PAGAR | E58: 45535 | F58: 000001001000001001 | G58: VLR PROVISAO BONUS | H58: 4.1.1.01.0026 | I58: 0302 | K58: 0 | L58: 28076 | M58: =L58*-1 -> -28076
B59: 2024 | C59: =MID(D59,1,12) -> 2.1.1.05.000 | D59: 2.1.1.05.0005 - PROVISAO BONUS A PAGAR | E59: 45412 | F59: 000001001000007002 | G59: 313 - PRÊMIO | H59: 3.1.1.04.0020 | I59: 0302 | K59: 31263.99 | L59: 0 | M59: 31263.99
B60: 2026 | C60: =MID(D60,1,12) -> 2.1.1.05.000 | D60: 2.1.1.05.0005 - PROVISAO BONUS A PAGAR | E60: 46203 | F60: WN2026001000004003 | G60: RECLAS.VLR FOPG 402 - DESCONTO DIVERSOS | H60: 4.4.1.01.0011 | I60: 0302 | J60: 0.3.2.000001 | K60: 0 | L60: 33571.79 | M60: =L60*-1 -> -33571.79
B61: 2024 | C61: =MID(D61,1,12) -> 2.1.1.05.000 | D61: 2.1.1.05.0005 - PROVISAO BONUS A PAGAR | E61: 45322 | F61: 000001001000004001 | G61: VLR PROVISAO DE BONUS | H61: 4.1.1.01.0026 | I61: 0301 | K61: 0 | L61: 39273 | M61: =L61*-1 -> -39273
B62: 2024 | C62: =MID(D62,1,12) -> 2.1.1.05.000 | D62: 2.1.1.05.0005 - PROVISAO BONUS A PAGAR | E62: 45536 | F62: 000001001000003001 | G62: VLR PROVISAO DE BONUS | H62: 4.1.1.01.0026 | I62: 0301 | K62: 40797 | L62: 0 | M62: 40797
B63: 2024 | C63: =MID(D63,1,12) -> 2.1.1.05.000 | D63: 2.1.1.05.0005 - PROVISAO BONUS A PAGAR | E63: 45595 | F63: 000001001000003001 | G63: VLR EST PREVISAO BONUS | H63: 4.1.1.01.0026 | I63: 0302 | K63: 42232 | L63: 0 | M63: 42232
B64: 2026 | C64: =MID(D64,1,12) -> 2.1.1.05.000 | D64: 2.1.1.05.0005 - PROVISAO BONUS A PAGAR | E64: 46203 | F64: WN2026001000004002 | G64: RECLAS.VLR FOPG 313 - PREMIO | H64: 4.1.1.01.0020 | I64: 0302 | K64: 44468.54 | L64: 0 | M64: 44468.54
B65: 2024 | C65: =MID(D65,1,12) -> 2.1.1.05.000 | D65: 2.1.1.05.0005 - PROVISAO BONUS A PAGAR | E65: 45352 | F65: 000001001000003001 | G65: VLR PROVISAO DE BONUS | H65: 4.1.1.01.0026 | I65: 0301 | K65: 0 | L65: 46472 | M65: =L65*-1 -> -46472
B66: 2024 | C66: =MID(D66,1,12) -> 2.1.1.05.000 | D66: 2.1.1.05.0005 - PROVISAO BONUS A PAGAR | E66: 45535 | F66: 000001001000004001 | G66: VLR PROVISAO DE BONUS | H66: 4.1.1.01.0026 | I66: 0301 | K66: 0 | L66: 46472 | M66: =L66*-1 -> -46472
B67: 2024 | C67: =MID(D67,1,12) -> 2.1.1.05.000 | D67: 2.1.1.05.0005 - PROVISAO BONUS A PAGAR | E67: 45382 | F67: 000001001000011001 | G67: VLR PROVISAO DE BONUS | H67: 4.1.1.01.0026 | I67: 0301 | K67: 0 | L67: 46473 | M67: =L67*-1 -> -46473
B68: 2024 | C68: =MID(D68,1,12) -> 2.1.1.05.000 | D68: 2.1.1.05.0005 - PROVISAO BONUS A PAGAR | E68: 45412 | F68: 000001001000006001 | G68: VLR PROVISAO DE BONUS | H68: 4.1.1.01.0026 | I68: 0301 | K68: 0 | L68: 46473 | M68: =L68*-1 -> -46473
B69: 2024 | C69: =MID(D69,1,12) -> 2.1.1.05.000 | D69: 2.1.1.05.0005 - PROVISAO BONUS A PAGAR | E69: 45443 | F69: 000001001000002001 | G69: VLR PROVISAO DE BONUS | H69: 4.1.1.01.0026 | I69: 0301 | K69: 0 | L69: 46473 | M69: =L69*-1 -> -46473
B70: 2024 | C70: =MID(D70,1,12) -> 2.1.1.05.000 | D70: 2.1.1.05.0005 - PROVISAO BONUS A PAGAR | E70: 45473 | F70: 000001001000002001 | G70: VLR PROVISAO DE BONUS | H70: 4.1.1.01.0026 | I70: 0301 | K70: 0 | L70: 46473 | M70: =L70*-1 -> -46473
B71: 2024 | C71: =MID(D71,1,12) -> 2.1.1.05.000 | D71: 2.1.1.05.0005 - PROVISAO BONUS A PAGAR | E71: 45504 | F71: 000001001000002001 | G71: VLR PROVISAO DE BONUS | H71: 4.1.1.01.0026 | I71: 0301 | K71: 0 | L71: 46473 | M71: =L71*-1 -> -46473
B72: 2024 | C72: =MID(D72,1,12) -> 2.1.1.05.000 | D72: 2.1.1.05.0005 - PROVISAO BONUS A PAGAR | E72: 45565 | F72: 000001001000003001 | G72: VLR PROVISAO BONUS | H72: 4.1.1.01.0026 | I72: 0302 | K72: 0 | L72: 48811 | M72: =L72*-1 -> -48811
B73: 2024 | C73: =MID(D73,1,12) -> 2.1.1.05.000 | D73: 2.1.1.05.0005 - PROVISAO BONUS A PAGAR | E73: 45382 | F73: 000001001000002001 | G73: VLR PROVISAO BONUS | H73: 4.1.1.01.0026 | I73: 0302 | K73: 0 | L73: 51772 | M73: =L73*-1 -> -51772
B74: 2024 | C74: =MID(D74,1,12) -> 2.1.1.05.000 | D74: 2.1.1.05.0005 - PROVISAO BONUS A PAGAR | E74: 45322 | F74: 000001001000005001 | G74: VLR PROVISAO BONUS | H74: 4.1.1.01.0026 | I74: 0302 | K74: 0 | L74: 51773 | M74: =L74*-1 -> -51773
B75: 2024 | C75: =MID(D75,1,12) -> 2.1.1.05.000 | D75: 2.1.1.05.0005 - PROVISAO BONUS A PAGAR | E75: 45351 | F75: 000001001000004001 | G75: VLR PROVISAO BONUS | H75: 4.1.1.01.0026 | I75: 0302 | K75: 0 | L75: 51773 | M75: =L75*-1 -> -51773
B76: 2024 | C76: =MID(D76,1,12) -> 2.1.1.05.000 | D76: 2.1.1.05.0005 - PROVISAO BONUS A PAGAR | E76: 45412 | F76: 000001001000004001 | G76: VLR PROVISAO BONUS | H76: 4.1.1.01.0026 | I76: 0302 | K76: 0 | L76: 51773 | M76: =L76*-1 -> -51773
B77: 2024 | C77: =MID(D77,1,12) -> 2.1.1.05.000 | D77: 2.1.1.05.0005 - PROVISAO BONUS A PAGAR | E77: 45443 | F77: 000001001000001001 | G77: VLR PROVISAO BONUS | H77: 4.1.1.01.0026 | I77: 0302 | K77: 0 | L77: 51773 | M77: =L77*-1 -> -51773
B78: 2024 | C78: =MID(D78,1,12) -> 2.1.1.05.000 | D78: 2.1.1.05.0005 - PROVISAO BONUS A PAGAR | E78: 45473 | F78: 000001001000001001 | G78: VLR PROVISAO BONUS | H78: 4.1.1.01.0026 | I78: 0302 | J78: 0.1.1.000001 | K78: 0 | L78: 51773 | M78: =L78*-1 -> -51773
B79: 2024 | C79: =MID(D79,1,12) -> 2.1.1.05.000 | D79: 2.1.1.05.0005 - PROVISAO BONUS A PAGAR | E79: 45504 | F79: 000001001000001001 | G79: VLR PROVISAO BONUS | H79: 4.1.1.01.0026 | I79: 0302 | K79: 0 | L79: 51773 | M79: =L79*-1 -> -51773
B80: 2024 | C80: =MID(D80,1,12) -> 2.1.1.05.000 | D80: 2.1.1.05.0005 - PROVISAO BONUS A PAGAR | E80: 45412 | F80: 99999B001000002001 | G80: 313 - PREMIO | H80: 4.1.1.01.0020 | I80: 0301 | J80: 0.3.5.000001 | K80: 55372.32 | L80: 0 | M80: 55372.32
B81: 2026 | C81: =MID(D81,1,12) -> 2.1.1.05.000 | D81: 2.1.1.05.0005 - PROVISAO BONUS A PAGAR | E81: 46142 | F81: WN2026001000004004 | G81: REV.VLR FOPG 313 - PREMIO | H81: 4.1.1.01.0020 | I81: 0302 | K81: 56492.33 | L81: 0 | M81: 56492.33
B82: 2023 | C82: =MID(D82,1,12) -> 2.1.1.05.000 | D82: 2.1.1.05.0005 - PROVISAO BONUS A PAGAR | E82: 45138 | F82: 000001001000015002 | G82: VLR PROVISAO BONUS | H82: 4.1.1.01.0026 | I82: 0301 | K82: 0 | L82: 56639 | M82: =L82*-1 -> -56639
B83: 2023 | C83: =MID(D83,1,12) -> 2.1.1.05.000 | D83: 2.1.1.05.0005 - PROVISAO BONUS A PAGAR | E83: 45199 | F83: 000001001000003002 | G83: VLR PROVISAO BONUS | H83: 4.1.1.01.0026 | I83: 0301 | K83: 0 | L83: 56639 | M83: =L83*-1 -> -56639
B84: 2023 | C84: =MID(D84,1,12) -> 2.1.1.05.000 | D84: 2.1.1.05.0005 - PROVISAO BONUS A PAGAR | E84: 45169 | F84: 000001001000003002 | G84: VLR PROVISAO BONUS | H84: 4.1.1.01.0026 | I84: 0301 | K84: 0 | L84: 56640 | M84: =L84*-1 -> -56640
B85: 2023 | C85: =MID(D85,1,12) -> 2.1.1.05.000 | D85: 2.1.1.05.0005 - PROVISAO BONUS A PAGAR | E85: 45230 | F85: 000001001000005002 | G85: VLR PROVISAO BONUS | H85: 4.1.1.01.0026 | I85: 0301 | K85: 0 | L85: 56640 | M85: =L85*-1 -> -56640
B86: 2024 | C86: =MID(D86,1,12) -> 2.1.1.05.000 | D86: 2.1.1.05.0005 - PROVISAO BONUS A PAGAR | E86: 45566 | F86: 000001001000001001 | G86: VLR PROVISAO DE BONUS | H86: 4.1.1.01.0026 | I86: 0301 | K86: 56880 | L86: 0 | M86: 56880
B87: 2022 | C87: =MID(D87,1,12) -> 2.1.1.05.000 | D87: 2.1.1.05.0005 - PROVISAO BONUS A PAGAR | E87: 44592 | F87: 000001001000019001 | G87: PROV BONUS | H87: 4.1.1.01.0026 | I87: 0301 | K87: 0 | L87: 59713.2 | M87: =L87*-1 -> -59713.2 | N87: Efeito zero
B88: 2022 | C88: =MID(D88,1,12) -> 2.1.1.05.000 | D88: 2.1.1.05.0005 - PROVISAO BONUS A PAGAR | E88: 44620 | F88: 000001001000022001 | G88: PROV BONUS | H88: 4.1.1.01.0026 | I88: 0301 | K88: 0 | L88: 59713.2 | M88: =L88*-1 -> -59713.2 | N88: Efeito zero
B89: 2022 | C89: =MID(D89,1,12) -> 2.1.1.05.000 | D89: 2.1.1.05.0005 - PROVISAO BONUS A PAGAR | E89: 44651 | F89: 000001001000001001 | G89: PROV BONUS | H89: 4.1.1.01.0026 | I89: 0301 | K89: 0 | L89: 59713.2 | M89: =L89*-1 -> -59713.2 | N89: Efeito zero
B90: 2022 | C90: =MID(D90,1,12) -> 2.1.1.05.000 | D90: 2.1.1.05.0005 - PROVISAO BONUS A PAGAR | E90: 44681 | F90: 000001001000007001 | G90: PROV BONUS | H90: 4.1.1.01.0026 | I90: 0301 | K90: 0 | L90: 59713.2 | M90: =L90*-1 -> -59713.2 | N90: Efeito zero
B91: 2022 | C91: =MID(D91,1,12) -> 2.1.1.05.000 | D91: 2.1.1.05.0005 - PROVISAO BONUS A PAGAR | E91: 44712 | F91: 000001001000002001 | G91: PROV BONUS | H91: 4.1.1.01.0026 | I91: 0301 | K91: 0 | L91: 59713.2 | M91: =L91*-1 -> -59713.2 | N91: Efeito zero
B92: 2022 | C92: =MID(D92,1,12) -> 2.1.1.05.000 | D92: 2.1.1.05.0005 - PROVISAO BONUS A PAGAR | E92: 44742 | F92: 000001001000009001 | G92: PROV BONUS | H92: 4.1.1.01.0026 | I92: 0301 | K92: 0 | L92: 59713.2 | M92: =L92*-1 -> -59713.2 | N92: Efeito zero
B93: 2022 | C93: =MID(D93,1,12) -> 2.1.1.05.000 | D93: 2.1.1.05.0005 - PROVISAO BONUS A PAGAR | E93: 44773 | F93: 000001001000001001 | G93: PROV BONUS | H93: 4.1.1.01.0026 | I93: 0301 | K93: 0 | L93: 59713.2 | M93: =L93*-1 -> -59713.2 | N93: Efeito zero
B94: 2022 | C94: =MID(D94,1,12) -> 2.1.1.05.000 | D94: 2.1.1.05.0005 - PROVISAO BONUS A PAGAR | E94: 44803 | F94: 000001001000001001 | G94: PROV BONUS | H94: 4.1.1.01.0026 | I94: 0301 | K94: 0 | L94: 59713.2 | M94: =L94*-1 -> -59713.2 | N94: Efeito zero
B95: 2022 | C95: =MID(D95,1,12) -> 2.1.1.05.000 | D95: 2.1.1.05.0005 - PROVISAO BONUS A PAGAR | E95: 44834 | F95: 000001001000002001 | G95: PROV BONUS | H95: 4.1.1.01.0026 | I95: 0301 | K95: 0 | L95: 59713.2 | M95: =L95*-1 -> -59713.2 | N95: Efeito zero
B96: 2022 | C96: =MID(D96,1,12) -> 2.1.1.05.000 | D96: 2.1.1.05.0005 - PROVISAO BONUS A PAGAR | E96: 44835 | F96: 000001001000009001 | G96: PROV BONUS | H96: 4.1.1.01.0026 | I96: 0301 | K96: 0 | L96: 59713.2 | M96: =L96*-1 -> -59713.2 | N96: Efeito zero
B97: 2025 | C97: =MID(D97,1,12) -> 2.1.1.05.000 | D97: 2.1.1.05.0005 - PROVISAO BONUS A PAGAR | E97: 45808 | F97: 000001001000005001 | G97: PROVISÃO BONUS-MAIO/25 | H97: 4.1.1.01.0026 | I97: 0301 | K97: 0 | L97: 62406 | M97: =L97*-1 -> -62406
B98: 2023 | C98: =MID(D98,1,12) -> 2.1.1.05.000 | D98: 2.1.1.05.0005 - PROVISAO BONUS A PAGAR | E98: 44957 | F98: 000001001000024001 | G98: PROV BONUS | H98: 4.1.1.01.0026 | I98: 0301 | K98: 0 | L98: 66439 | M98: =L98*-1 -> -66439
B99: 2023 | C99: =MID(D99,1,12) -> 2.1.1.05.000 | D99: 2.1.1.05.0005 - PROVISAO BONUS A PAGAR | E99: 44985 | F99: 000001001000012001 | G99: PROV BONUS | H99: 4.1.1.01.0026 | I99: 0301 | K99: 0 | L99: 66439 | M99: =L99*-1 -> -66439
B100: 2023 | C100: =MID(D100,1,12) -> 2.1.1.05.000 | D100: 2.1.1.05.0005 - PROVISAO BONUS A PAGAR | E100: 45016 | F100: 000001001000005001 | G100: PROV BONUS | H100: 4.1.1.01.0026 | I100: 0301 | K100: 0 | L100: 66439 | M100: =L100*-1 -> -66439
B101: 2023 | C101: =MID(D101,1,12) -> 2.1.1.05.000 | D101: 2.1.1.05.0005 - PROVISAO BONUS A PAGAR | E101: 45077 | F101: 000001001011342001 | G101: VLR PROVISAO BONUS | H101: 4.1.1.01.0026 | I101: 0301 | K101: 0 | L101: 66439 | M101: =L101*-1 -> -66439
B102: 2023 | C102: =MID(D102,1,12) -> 2.1.1.05.000 | D102: 2.1.1.05.0005 - PROVISAO BONUS A PAGAR | E102: 45046 | F102: 000001001000016001 | G102: PROV BONUS | H102: 4.1.1.01.0026 | I102: 0301 | K102: 0 | L102: 66440 | M102: =L102*-1 -> -66440
B103: 2024 | C103: =MID(D103,1,12) -> 2.1.1.05.000 | D103: 2.1.1.05.0005 - PROVISAO BONUS A PAGAR | E103: 45387 | F103: 008850001000001001 | G103: VLR PG FOL 000003388- FOLHA DE PAGAMENTO SALARIOS E ORDENADOS | H103: 1.1.1.02.0024 | I103: 0302 | K103: 71574.93 | L103: 0 | M103: 71574.93 | N103: Efeito zero
...

Sheet Capa
D2: SIGLA | E2: EMPRESA | J2: Emissão
D3: 01101 | E3: AMBAR TECH | J3: =TODAY() -> 46220
D4: GRUPO CONTÁBIL | E4: DESCRIÇÃO DO GRUPO | J4: PERIODO
J5: jun/26
D6: 2.1.5.00.000 | E6: OUTRAS OBRIGACOES
B9: Conta | C9: Descrição da Conta | G9: Balancete | H9: Relatorio Auxiliar | I9: Diferença
B10: 2.1.5.10.050 | C10: =_xlfn.XLOOKUP(B10,'00.Balancete'!E:E,'00.Balancete'!F:F) -> #N/A | G10: =-SUMIFS('00.Balancete'!$N:$N,'00.Balancete'!$E:$E,Capa!$B10) -> 0 | H10: ='02.Suporte'!Q7 -> 595920 | I10: =G10-H10 -> -595920
B13: DIFERENÇA ( 1 ) - ( 2 ) = ( 3 ) | G13: =SUM(G10:G10) -> 0 | H13: =SUM(H10:H10) -> 595920 | I13: =SUM(I10:I11) -> -595920
B15: COMPOSIÇÃO DA DIFERENÇA
B17: DATA | C17: DIFERENÇAS IDENTIFICADAS NA CONTABILIDADE | G17: Status | H17: Conta Débito | I17: Conta Crédito | J17: VALOR
B18: 45291 | C18: Saldo baixado a maior referente a provisão de Bônus - 2023 | H18: 5.1.3.80.140 | I18: 2.1.5.10.050 | J18: =-SUMIFS('03.Conciliação'!$E:$E,'03.Conciliação'!$F:$F,Capa!$C18) -> 0
B19: 45657 | C19: Saldo em aberto referente a Provisão de Bônus - 2024 | H19: 2.1.5.10.050 | I19: 5.1.3.80.140 | J19: =-SUMIFS('03.Conciliação'!$E:$E,'03.Conciliação'!$F:$F,Capa!$C19) -> 0
B20: 46022 | C20: Saldo em aberto referente a Provisão de Bônus - 2025 | H20: 2.1.5.10.050 | I20: 5.1.3.80.140 | J20: =-SUMIFS('03.Conciliação'!$E:$E,'03.Conciliação'!$F:$F,Capa!$C20) -> 0
B22: TOTAL ( 4 ) | J22: =SUM(J18:J21) -> 0
B24: DATA | C24: DIFERENÇAS IDENTIFICADAS NO RELATÓRIO | G24: Status | H24: Conta Débito | I24: Conta Crédito | J24: VALOR
J27: =IF(G27=0," ",IF(G27<0,"C","D"))
B28: TOTAL ( 5 ) | J28: =SUM(J25:J27) -> 0
B30: DIFERENÇA A IDENITIFICAR ( 3 ) - ( 4 ) - ( 5 ) | J30: =I13-J22-J28 -> -595920
B32: OBSERVAÇÕES: | E32: Prepado por : | G32: Revisado por: | H32: Aprovado por:
E33: Willian Nascimento | G33: Willian Nascimento
E34: =J3 -> 46220 | G34: 46204

Sheet 00.Balancete
M1: Ativo | N1: =SUMIFS($N$8:$N$407,$C$8:$C$407,$M1) -> 53511864
M2: Passivo | N2: =SUMIFS($N$8:$N$407,$C$8:$C$407,$M2) -> -1.2466241e+08
M3: Resultado | N3: =SUMIFS($N$8:$N$407,$C$8:$C$407,$M3) -> 7940390.2
M4: Check | N4: =SUM(N1:N3) -> -63210158
M6: =SUBTOTAL(9,M8:M407) -> -2.7677743e-08 | N6: =SUBTOTAL(9,N8:N407) -> -1.1916563e-07
B7: Período | C7: Classe | D7: Tipo | E7: Conta | F7: Descricao | G7: 31.12.25 | I7: DB | J7: CR | K7: 30.06.26 | M7: =G7 -> 31.12.25 | N7: =K7 -> 30.06.26 | O7: Obs.
B8: jun/26 | D8: =IF(MID(E8,10,3)="000","Sintetica","") -> Sintetica | E8: 1.0.0.00.0000 | F8: ATIVO | G8: 23463932 | H8: D | I8: 5841042 | J8: 5685303.1 | K8: 23619671 | L8: D | M8: =IF(H8="D",G8,-G8) -> 23463932 | N8: =IF(L8="D",K8,-K8) -> 23619671
B9: jun/26 | D9: =IF(MID(E9,10,3)="000","Sintetica","") -> Sintetica | E9: 1.1.0.00.0000 | F9: ATIVO CIRCULANTE | G9: 21423978 | H9: D | I9: 5818427 | J9: 5630446 | K9: 21611959 | L9: D | M9: =IF(H9="D",G9,-G9) -> 21423978 | N9: =IF(L9="D",K9,-K9) -> 21611959
B10: jun/26 | D10: =IF(MID(E10,10,3)="000","Sintetica","") -> Sintetica | E10: 1.1.1.00.0000 | F10: DISPONIVEL | G10: 1931841.1 | H10: D | I10: 4018479.6 | J10: 4225853.2 | K10: 1724467.5 | L10: D | M10: =IF(H10="D",G10,-G10) -> 1931841.1 | N10: =IF(L10="D",K10,-K10) -> 1724467.5
B11: jun/26 | D11: =IF(MID(E11,10,3)="000","Sintetica","") -> Sintetica | E11: 1.1.1.02.0000 | F11: BANCOS CONTA MOVIMENTO | G11: 782820.75 | H11: D | I11: 4018408.1 | J11: 4225167.1 | K11: 576061.72 | L11: D | M11: =IF(H11="D",G11,-G11) -> 782820.75 | N11: =IF(L11="D",K11,-K11) -> 576061.72
B12: jun/26 | C12: =IF(MID(E12,1,1)="1","Ativo",IF(MID(E12,1,1)="2","Passivo","Resultado")) -> Ativo | D12: =IF(MID(E12,10,3)="000","Sintetica","") | E12: 1.1.1.02.0010 | F12: BRADESCO S/A - SMART PODS | G12: 0 | I12: 1530143.8 | J12: 1530143.8 | K12: 0 | M12: =IF(H12="D",G12,-G12) -> 0 | N12: =IF(L12="D",K12,-K12) -> 0
B13: jun/26 | D13: =IF(MID(E13,10,3)="000","Sintetica","") | E13: 1.1.1.02.0011 | F13: ITAU S/A - SMART PODS | G13: 72.52 | H13: D | I13: 673.68 | J13: 1108.89 | K13: 362.69 | L13: C | M13: =IF(H13="D",G13,-G13) -> 72.52 | N13: =IF(L13="D",K13,-K13) -> -362.69
B14: jun/26 | C14: =IF(MID(E14,1,1)="1","Ativo",IF(MID(E14,1,1)="2","Passivo","Resultado")) -> Ativo | D14: =IF(MID(E14,10,3)="000","Sintetica","") | E14: 1.1.1.02.0013 | F14: BANCO DO BRASIL - SMART PODS | G14: 0 | I14: 30194.16 | J14: 30194.16 | K14: 0 | M14: =IF(H14="D",G14,-G14) -> 0 | N14: =IF(L14="D",K14,-K14) -> 0
B15: jun/26 | C15: =IF(MID(E15,1,1)="1","Ativo",IF(MID(E15,1,1)="2","Passivo","Resultado")) -> Ativo | D15: =IF(MID(E15,10,3)="000","Sintetica","") | E15: 1.1.1.02.0014 | F15: BANCO SANTANDER - SMART PODS | G15: 0 | I15: 76211.55 | J15: 175971.45 | K15: 99759.9 | L15: C | M15: =IF(H15="D",G15,-G15) -> 0 | N15: =IF(L15="D",K15,-K15) -> -99759.9
B16: jun/26 | C16: =IF(MID(E16,1,1)="1","Ativo",IF(MID(E16,1,1)="2","Passivo","Resultado")) -> Ativo | D16: =IF(MID(E16,10,3)="000","Sintetica","") | E16: 1.1.1.02.0015 | F16: BANCO BOCOM BBM - SMART PODS | G16: 471.4 | H16: D | I16: 0 | J16: 0 | K16: 471.4 | L16: D | M16: =IF(H16="D",G16,-G16) -> 471.4 | N16: =IF(L16="D",K16,-K16) -> 471.4
B17: jun/26 | C17: =IF(MID(E17,1,1)="1","Ativo",IF(MID(E17,1,1)="2","Passivo","Resultado")) -> Ativo | D17: =IF(MID(E17,10,3)="000","Sintetica","") | E17: 1.1.1.02.0016 | F17: BANCO ABC C.C MATRIZ | G17: 267.21 | H17: D | I17: 105091.29 | J17: 102592.6 | K17: 2765.9 | L17: D | M17: =IF(H17="D",G17,-G17) -> 267.21 | N17: =IF(L17="D",K17,-K17) -> 2765.9
B18: jun/26 | C18: =IF(MID(E18,1,1)="1","Ativo",IF(MID(E18,1,1)="2","Passivo","Resultado")) -> Ativo | D18: =IF(MID(E18,10,3)="000","Sintetica","") | E18: 1.1.1.02.0017 | F18: BANCO SOFISA VINC. AG. 19 CC. 14293503 | G18: 781880.95 | H18: D | I18: 153.52 | J18: 181955.06 | K18: 600079.41 | L18: D | M18: =IF(H18="D",G18,-G18) -> 781880.95 | N18: =IF(L18="D",K18,-K18) -> 600079.41
B19: jun/26 | C19: =IF(MID(E19,1,1)="1","Ativo",IF(MID(E19,1,1)="2","Passivo","Resultado")) -> Ativo | D19: =IF(MID(E19,10,3)="000","Sintetica","") | E19: 1.1.1.02.0024 | F19: BANCO SANTANDER - SMART FILIAL | G19: 0 | I19: 1756685.2 | J19: 1757043 | K19: 357.77 | L19: C | M19: =IF(H19="D",G19,-G19) -> 0 | N19: =IF(L19="D",K19,-K19) -> -357.77
B20: jun/26 | C20: =IF(MID(E20,1,1)="1","Ativo",IF(MID(E20,1,1)="2","Passivo","Resultado")) -> Ativo | D20: =IF(MID(E20,10,3)="000","Sintetica","") | E20: 1.1.1.02.0025 | F20: BANCO SOFISA AG. 00019 CC.13649169 MATR | G20: 0 | I20: 90880.34 | J20: 17622.29 | K20: 73258.05 | L20: D | M20: =IF(H20="D",G20,-G20) -> 0 | N20: =IF(L20="D",K20,-K20) -> 73258.05
B21: jun/26 | C21: =IF(MID(E21,1,1)="1","Ativo",IF(MID(E21,1,1)="2","Passivo","Resultado")) -> Ativo | D21: =IF(MID(E21,10,3)="000","Sintetica","") | E21: 1.1.1.02.0026 | F21: BANCO DAYCOVAL - AG. 00019 CC 15147454 | G21: 127.13 | H21: D | I21: 0 | J21: 43.79 | K21: 83.34 | L21: D | M21: =IF(H21="D",G21,-G21) -> 127.13 | N21: =IF(L21="D",K21,-K21) -> 83.34
B22: jun/26 | C22: =IF(MID(E22,1,1)="1","Ativo",IF(MID(E22,1,1)="2","Passivo","Resultado")) -> Ativo | D22: =IF(MID(E22,10,3)="000","Sintetica","") | E22: 1.1.1.02.0028 | F22: BANCO ABC AG.019 CC.23317770 CC FILIAL | G22: 1.54 | H22: D | I22: 1734.41 | J22: 1851.97 | K22: 116.02 | L22: C | M22: =IF(H22="D",G22,-G22) -> 1.54 | N22: =IF(L22="D",K22,-K22) -> -116.02
B23: jun/26 | C23: =IF(MID(E23,1,1)="1","Ativo",IF(MID(E23,1,1)="2","Passivo","Resultado")) -> Ativo | D23: =IF(MID(E23,10,3)="000","Sintetica","") | E23: 1.1.1.02.9999 | F23: BANCOS TRANSFERENCIAS ENTRE FILIAIS | G23: 0 | I23: 426640.15 | J23: 426640.15 | K23: 0 | M23: =IF(H23="D",G23,-G23) -> 0 | N23: =IF(L23="D",K23,-K23) -> 0
B24: jun/26 | C24: =IF(MID(E24,1,1)="1","Ativo",IF(MID(E24,1,1)="2","Passivo","Resultado")) -> Ativo | D24: =IF(MID(E24,10,3)="000","Sintetica","") -> Sintetica | E24: 1.1.1.03.0000 | F24: APLICACOES FINANCEIRAS | G24: 1149020.3 | H24: D | I24: 71.53 | J24: 686.09 | K24: 1148405.8 | L24: D | M24: =IF(H24="D",G24,-G24) -> 1149020.3 | N24: =IF(L24="D",K24,-K24) -> 1148405.8
B25: jun/26 | C25: =IF(MID(E25,1,1)="1","Ativo",IF(MID(E25,1,1)="2","Passivo","Resultado")) -> Ativo | D25: =IF(MID(E25,10,3)="000","Sintetica","") | E25: 1.1.1.03.0011 | F25: ITAU S/A - SMART PODS | G25: 420.41 | H25: D | I25: 71.52 | J25: 491.93 | K25: 0 | M25: =IF(H25="D",G25,-G25) -> 420.41 | N25: =IF(L25="D",K25,-K25) -> 0
B26: jun/26 | C26: =IF(MID(E26,1,1)="1","Ativo",IF(MID(E26,1,1)="2","Passivo","Resultado")) -> Ativo | D26: =IF(MID(E26,10,3)="000","Sintetica","") | E26: 1.1.1.03.0025 | F26: APLIC BANCO ABC - SMART PODS | G26: 1148405.8 | H26: D | I26: 0 | J26: 0 | K26: 1148405.8 | L26: D | M26: =IF(H26="D",G26,-G26) -> 1148405.8 | N26: =IF(L26="D",K26,-K26) -> 1148405.8
B27: jun/26 | C27: =IF(MID(E27,1,1)="1","Ativo",IF(MID(E27,1,1)="2","Passivo","Resultado")) -> Ativo | D27: =IF(MID(E27,10,3)="000","Sintetica","") | E27: 1.1.1.03.0027 | F27: APLICAÇÃO BB RENDE FÁCIL MATRIZ | G27: 194.15 | H27: D | I27: 0.01 | J27: 194.16 | K27: 0 | M27: =IF(H27="D",G27,-G27) -> 194.15 | N27: =IF(L27="D",K27,-K27) -> 0
B28: jun/26 | D28: =IF(MID(E28,10,3)="000","Sintetica","") -> Sintetica | E28: 1.1.2.00.0000 | F28: CREDITOS | G28: 10712086 | H28: D | I28: 869998.15 | J28: 749155.56 | K28: 10832929 | L28: D | M28: =IF(H28="D",G28,-G28) -> 10712086 | N28: =IF(L28="D",K28,-K28) -> 10832929
B29: jun/26 | C29: =IF(MID(E29,1,1)="1","Ativo",IF(MID(E29,1,1)="2","Passivo","Resultado")) -> Ativo | D29: =IF(MID(E29,10,3)="000","Sintetica","") -> Sintetica | E29: 1.1.2.01.0000 | F29: CLIENTES | G29: 10759086 | H29: D | I29: 818931.59 | J29: 697830.41 | K29: 10880187 | L29: D | M29: =IF(H29="D",G29,-G29) -> 10759086 | N29: =IF(L29="D",K29,-K29) -> 10880187
B30: jun/26 | C30: =IF(MID(E30,1,1)="1","Ativo",IF(MID(E30,1,1)="2","Passivo","Resultado")) -> Ativo | D30: =IF(MID(E30,10,3)="000","Sintetica","") -> Sintetica | E30: 1.1.2.01.0001 | F30: CONTAS A RECEBER | G30: 10595294 | H30: D | I30: 802315.34 | J30: 681214.16 | K30: 10716395 | L30: D | M30: =IF(H30="D",G30,-G30) -> 10595294 | N30: =IF(L30="D",K30,-K30) -> 10716395
B31: jun/26 | C31: =IF(MID(E31,1,1)="1","Ativo",IF(MID(E31,1,1)="2","Passivo","Resultado")) -> Ativo | D31: =IF(MID(E31,10,3)="000","Sintetica","") -> Sintetica | E31: 1.1.2.01.0002 | F31: (-) DEVOLUCAO CLIENTES COMPENSAR | G31: 3518166.4 | H31: C | I31: 0 | J31: 0 | K31: 3518166.4 | L31: C | M31: =IF(H31="D",G31,-G31) -> -3518166.4 | N31: =IF(L31="D",K31,-K31) -> -3518166.4
B32: jun/26 | C32: =IF(MID(E32,1,1)="1","Ativo",IF(MID(E32,1,1)="2","Passivo","Resultado")) -> Ativo | D32: =IF(MID(E32,10,3)="000","Sintetica","") -> Sintetica | E32: 1.1.2.01.0003 | F32: ANTECIPACAO DE CLIENTES A RECEBER | G32: 541323.32 | H32: D | I32: 0 | J32: 0 | K32: 541323.32 | L32: D | M32: =IF(H32="D",G32,-G32) -> 541323.32 | N32: =IF(L32="D",K32,-K32) -> 541323.32
B33: jun/26 | C33: =IF(MID(E33,1,1)="1","Ativo",IF(MID(E33,1,1)="2","Passivo","Resultado")) -> Ativo | D33: =IF(MID(E33,10,3)="000","Sintetica","") -> Sintetica | E33: 1.1.2.01.0007 | F33: (-) PROV P/ CRED DE LIQUIDACAO DUVID | G33: 1260020.9 | H33: C | I33: 0 | J33: 0 | K33: 1260020.9 | L33: C | M33: =IF(H33="D",G33,-G33) -> -1260020.9 | N33: =IF(L33="D",K33,-K33) -> -1260020.9
B34: jun/26 | C34: =IF(MID(E34,1,1)="1","Ativo",IF(MID(E34,1,1)="2","Passivo","Resultado")) -> Ativo | D34: =IF(MID(E34,10,3)="000","Sintetica","") -> Sintetica | E34: 1.1.2.01.0008 | F34: PROVISAO SERVIÇOS A REALIZAR | G34: 3426105 | H34: D | I34: 0 | J34: 0 | K34: 3426105 | L34: D | M34: =IF(H34="D",G34,-G34) -> 3426105 | N34: =IF(L34="D",K34,-K34) -> 3426105
B35: jun/26 | C35: =IF(MID(E35,1,1)="1","Ativo",IF(MID(E35,1,1)="2","Passivo","Resultado")) -> Ativo | D35: =IF(MID(E35,10,3)="000","Sintetica","") | E35: 1.1.2.01.0010 | F35: CONTAS A RECEBER INTERCO | G35: 433227.56 | H35: D | I35: 12063 | J35: 12063 | K35: 433227.56 | L35: D | M35: =IF(H35="D",G35,-G35) -> 433227.56 | N35: =IF(L35="D",K35,-K35) -> 433227.56
B36: jun/26 | C36: =IF(MID(E36,1,1)="1","Ativo",IF(MID(E36,1,1)="2","Passivo","Resultado")) -> Ativo | D36: =IF(MID(E36,10,3)="000","Sintetica","") | E36: 1.1.2.01.9998 | F36: CLIENTES - FATURAMENTO ANTECIPADO | G36: 1516728.8 | H36: D | I36: 0 | J36: 4553.25 | K36: 1512175.5 | L36: D | M36: =IF(H36="D",G36,-G36) -> 1516728.8 | N36: =IF(L36="D",K36,-K36) -> 1512175.5
B37: jun/26 | C37: =IF(MID(E37,1,1)="1","Ativo",IF(MID(E37,1,1)="2","Passivo","Resultado")) -> Ativo | D37: =IF(MID(E37,10,3)="000","Sintetica","") | E37: 1.1.2.01.9999 | F37: (-) FATURAMENTO ANTECIPADO | G37: 975405.43 | H37: C | I37: 4553.25 | J37: 0 | K37: 970852.18 | L37: C | M37: =IF(H37="D",G37,-G37) -> -975405.43 | N37: =IF(L37="D",K37,-K37) -> -970852.18
B38: jun/26 | C38: =IF(MID(E38,1,1)="1","Ativo",IF(MID(E38,1,1)="2","Passivo","Resultado")) -> Ativo | D38: =IF(MID(E38,10,3)="000","Sintetica","") -> Sintetica | E38: 1.1.2.02.0000 | F38: CREDITOS DE PESSOAL | G38: 46999.81 | H38: C | I38: 51066.56 | J38: 51325.15 | K38: 47258.4 | L38: C | M38: =IF(H38="D",G38,-G38) -> -46999.81 | N38: =IF(L38="D",K38,-K38) -> -47258.4
B39: jun/26 | C39: =IF(MID(E39,1,1)="1","Ativo",IF(MID(E39,1,1)="2","Passivo","Resultado")) -> Ativo | D39: =IF(MID(E39,10,3)="000","Sintetica","") -> Sintetica | E39: 1.1.2.02.0001 | F39: ADIANTAMENTO DE SALARIOS | G39: 49546.52 | H39: C | I39: 49546.52 | J39: 50003.75 | K39: 50003.75 | L39: C | M39: =IF(H39="D",G39,-G39) -> -49546.52 | N39: =IF(L39="D",K39,-K39) -> -50003.75
B40: jun/26 | D40: =IF(MID(E40,10,3)="000","Sintetica","") -> Sintetica | E40: 1.1.2.02.0002 | F40: ADIANTAMENTO DE FERIAS | G40: 303.63 | H40: C | I40: 303.63 | J40: 271.89 | K40: 271.89 | L40: C | M40: =IF(H40="D",G40,-G40) -> -303.63 | N40: =IF(L40="D",K40,-K40) -> -271.89
B41: jun/26 | D41: =IF(MID(E41,10,3)="000","Sintetica","") -> Sintetica | E41: 1.1.2.02.0004 | F41: EMPRESTIMO COLABORADORES | G41: 2850.34 | H41: D | I41: 1216.41 | J41: 1049.51 | K41: 3017.24 | L41: D | M41: =IF(H41="D",G41,-G41) -> 2850.34 | N41: =IF(L41="D",K41,-K41) -> 3017.24
B42: jun/26 | C42: =IF(MID(E42,1,1)="1","Ativo",IF(MID(E42,1,1)="2","Passivo","Resultado")) -> Ativo | D42: =IF(MID(E42,10,3)="000","Sintetica","") -> Sintetica | E42: 1.1.3.00.0000 | F42: ADIANTAMENTOS DIVERSOS | G42: 1579453.6 | H42: D | I42: 450644.86 | J42: 288728.59 | K42: 1741369.9 | L42: D | M42: =IF(H42="D",G42,-G42) -> 1579453.6 | N42: =IF(L42="D",K42,-K42) -> 1741369.9
B43: jun/26 | C43: =IF(MID(E43,1,1)="1","Ativo",IF(MID(E43,1,1)="2","Passivo","Resultado")) -> Ativo | D43: =IF(MID(E43,10,3)="000","Sintetica","") -> Sintetica | E43: 1.1.3.01.0000 | F43: ADIANTAMENTO A FORNECEDORES | G43: 1579453.6 | H43: D | I43: 450644.86 | J43: 288728.59 | K43: 1741369.9 | L43: D | M43: =IF(H43="D",G43,-G43) -> 1579453.6 | N43: =IF(L43="D",K43,-K43) -> 1741369.9
B44: jun/26 | C44: =IF(MID(E44,1,1)="1","Ativo",IF(MID(E44,1,1)="2","Passivo","Resultado")) -> Ativo | D44: =IF(MID(E44,10,3)="000","Sintetica","") -> Sintetica | E44: 1.1.3.01.0003 | F44: ADIANTAMENTO FORNECEDORES | G44: 669262.92 | H44: D | I44: 450644.86 | J44: 288728.59 | K44: 831179.19 | L44: D | M44: =IF(H44="D",G44,-G44) -> 669262.92 | N44: =IF(L44="D",K44,-K44) -> 831179.19
B45: jun/26 | C45: =IF(MID(E45,1,1)="1","Ativo",IF(MID(E45,1,1)="2","Passivo","Resultado")) -> Ativo | D45: =IF(MID(E45,10,3)="000","Sintetica","") -> Sintetica | E45: 1.1.3.01.0004 | F45: ADIANTAMENTO FORNECEDORES EXTERIOR | G45: 798988.5 | H45: D | I45: 0 | J45: 0 | K45: 798988.5 | L45: D | M45: =IF(H45="D",G45,-G45) -> 798988.5 | N45: =IF(L45="D",K45,-K45) -> 798988.5
B46: jun/26 | C46: =IF(MID(E46,1,1)="1","Ativo",IF(MID(E46,1,1)="2","Passivo","Resultado")) -> Ativo | D46: =IF(MID(E46,10,3)="000","Sintetica","") -> Sintetica | E46: 1.1.3.01.0005 | F46: OUTROS ADIANTAMENTOS DIVERSOS | G46: 111202.22 | H46: D | I46: 0 | J46: 0 | K46: 111202.22 | L46: D | M46: =IF(H46="D",G46,-G46) -> 111202.22 | N46: =IF(L46="D",K46,-K46) -> 111202.22
B47: jun/26 | C47: =IF(MID(E47,1,1)="1","Ativo",IF(MID(E47,1,1)="2","Passivo","Resultado")) -> Ativo | D47: =IF(MID(E47,10,3)="000","Sintetica","") -> Sintetica | E47: 1.1.4.00.0000 | F47: ESTOQUES | G47: 2450981.5 | H47: D | I47: 376979.7 | J47: 338308.28 | K47: 2489653 | L47: D | M47: =IF(H47="D",G47,-G47) -> 2450981.5 | N47: =IF(L47="D",K47,-K47) -> 2489653
B48: jun/26 | D48: =IF(MID(E48,10,3)="000","Sintetica","") -> Sintetica | E48: 1.1.4.01.0000 | F48: ESTOQUES | G48: 2450981.5 | H48: D | I48: 376979.7 | J48: 338308.28 | K48: 2489653 | L48: D | M48: =IF(H48="D",G48,-G48) -> 2450981.5 | N48: =IF(L48="D",K48,-K48) -> 2489653
B49: jun/26 | C49: =IF(MID(E49,1,1)="1","Ativo",IF(MID(E49,1,1)="2","Passivo","Resultado")) -> Ativo | D49: =IF(MID(E49,10,3)="000","Sintetica","") -> Sintetica | E49: 1.1.4.01.0001 | F49: MATERIA PRIMA | G49: 2205374.3 | H49: D | I49: 232242.86 | J49: 204088.99 | K49: 2233528.2 | L49: D | M49: =IF(H49="D",G49,-G49) -> 2205374.3 | N49: =IF(L49="D",K49,-K49) -> 2233528.2
B50: jun/26 | D50: =IF(MID(E50,10,3)="000","Sintetica","") -> Sintetica | E50: 1.1.4.01.0002 | F50: INSUMOS | G50: 49.63 | H50: D | I50: 0 | J50: 0 | K50: 49.63 | L50: D | M50: =IF(H50="D",G50,-G50) -> 49.63 | N50: =IF(L50="D",K50,-K50) -> 49.63
B51: jun/26 | D51: =IF(MID(E51,10,3)="000","Sintetica","") -> Sintetica | E51: 1.1.4.01.0004 | F51: PRODUTOS EM ELABORACAO POR TERCEIROS | G51: 86374.71 | H51: D | I51: 0 | J51: 0 | K51: 86374.71 | L51: D | M51: =IF(H51="D",G51,-G51) -> 86374.71 | N51: =IF(L51="D",K51,-K51) -> 86374.71
B52: jun/26 | C52: =IF(MID(E52,1,1)="1","Ativo",IF(MID(E52,1,1)="2","Passivo","Resultado")) -> Ativo | D52: =IF(MID(E52,10,3)="000","Sintetica","") -> Sintetica | E52: 1.1.4.01.0005 | F52: PRODUTOS INTERMEDIARIOS | G52: 158250 | H52: D | I52: 9447.34 | J52: 461.9 | K52: 167235.44 | L52: D | M52: =IF(H52="D",G52,-G52) -> 158250 | N52: =IF(L52="D",K52,-K52) -> 167235.44
B53: jun/26 | C53: =IF(MID(E53,1,1)="1","Ativo",IF(MID(E53,1,1)="2","Passivo","Resultado")) -> Ativo | D53: =IF(MID(E53,10,3)="000","Sintetica","") -> Sintetica | E53: 1.1.4.01.0006 | F53: PRODUTOS ACABADOS | G53: 382159.94 | H53: D | I53: 134969.5 | J53: 133675.53 | K53: 383453.91 | L53: D | M53: =IF(H53="D",G53,-G53) -> 382159.94 | N53: =IF(L53="D",K53,-K53) -> 383453.91
B54: jun/26 | C54: =IF(MID(E54,1,1)="1","Ativo",IF(MID(E54,1,1)="2","Passivo","Resultado")) -> Ativo | D54: =IF(MID(E54,10,3)="000","Sintetica","") -> Sintetica | E54: 1.1.4.01.0007 | F54: MERCADORIAS PARA REVENDA | G54: 9367.48 | H54: D | I54: 320 | J54: 81.86 | K54: 9605.62 | L54: D | M54: =IF(H54="D",G54,-G54) -> 9367.48 | N54: =IF(L54="D",K54,-K54) -> 9605.62
B55: jun/26 | C55: =IF(MID(E55,1,1)="1","Ativo",IF(MID(E55,1,1)="2","Passivo","Resultado")) -> Ativo | D55: =IF(MID(E55,10,3)="000","Sintetica","") | E55: 1.1.4.01.0010 | F55: FATURAMENTO ANTECIPADO | G55: 0.02 | H55: D | I55: 0 | J55: 0 | K55: 0.02 | L55: D | M55: =IF(H55="D",G55,-G55) -> 0.02 | N55: =IF(L55="D",K55,-K55) -> 0.02
B56: jun/26 | C56: =IF(MID(E56,1,1)="1","Ativo",IF(MID(E56,1,1)="2","Passivo","Resultado")) -> Ativo | D56: =IF(MID(E56,10,3)="000","Sintetica","") | E56: 1.1.4.01.0013 | F56: (-) PROV. DE MATERIA PRIMA | G56: 186430.43 | H56: C | I56: 0 | J56: 0 | K56: 186430.43 | L56: C | M56: =IF(H56="D",G56,-G56) -> -186430.43 | N56: =IF(L56="D",K56,-K56) -> -186430.43
B57: jun/26 | C57: =IF(MID(E57,1,1)="1","Ativo",IF(MID(E57,1,1)="2","Passivo","Resultado")) -> Ativo | D57: =IF(MID(E57,10,3)="000","Sintetica","") | E57: 1.1.4.01.9995 | F57: TRANSFERENCIA ESTOQUE MATRIZ FILIAL | G57: 5458.24 | H57: D | I57: 0 | J57: 0 | K57: 5458.24 | L57: D | M57: =IF(H57="D",G57,-G57) -> 5458.24 | N57: =IF(L57="D",K57,-K57) -> 5458.24
B58: jun/26 | C58: =IF(MID(E58,1,1)="1","Ativo",IF(MID(E58,1,1)="2","Passivo","Resultado")) -> Ativo | D58: =IF(MID(E58,10,3)="000","Sintetica","") | E58: 1.1.4.01.9996 | F58: (-) PROVISAO ESTOQUE OBSOLETO | G58: 210462.12 | H58: C | I58: 0 | J58: 0 | K58: 210462.12 | L58: C | M58: =IF(H58="D",G58,-G58) -> -210462.12 | N58: =IF(L58="D",K58,-K58) -> -210462.12
B59: jun/26 | C59: =IF(MID(E59,1,1)="1","Ativo",IF(MID(E59,1,1)="2","Passivo","Resultado")) -> Ativo | D59: =IF(MID(E59,10,3)="000","Sintetica","") | E59: 1.1.4.01.9999 | F59: MERCADORIAS DEMONSTRACAO EM NOSSO PODER | G59: 839.77 | H59: D | I59: 0 | J59: 0 | K59: 839.77 | L59: D | M59: =IF(H59="D",G59,-G59) -> 839.77 | N59: =IF(L59="D",K59,-K59) -> 839.77
B60: jun/26 | C60: =IF(MID(E60,1,1)="1","Ativo",IF(MID(E60,1,1)="2","Passivo","Resultado")) -> Ativo | D60: =IF(MID(E60,10,3)="000","Sintetica","") -> Sintetica | E60: 1.1.5.00.0000 | F60: CREDITOS TRIBUTARIOS | G60: 4391783.1 | H60: D | I60: 102115.32 | J60: 11400.8 | K60: 4482497.6 | L60: D | M60: =IF(H60="D",G60,-G60) -> 4391783.1 | N60: =IF(L60="D",K60,-K60) -> 4482497.6
B61: jun/26 | C61: =IF(MID(E61,1,1)="1","Ativo",IF(MID(E61,1,1)="2","Passivo","Resultado")) -> Ativo | D61: =IF(MID(E61,10,3)="000","Sintetica","") -> Sintetica | E61: 1.1.5.01.0000 | F61: IMPOSTOS E CONTRIBUICOES A RECUPERAR | G61: 4391783.1 | H61: D | I61: 102115.32 | J61: 11400.8 | K61: 4482497.6 | L61: D | M61: =IF(H61="D",G61,-G61) -> 4391783.1 | N61: =IF(L61="D",K61,-K61) -> 4482497.6
B62: jun/26 | C62: =IF(MID(E62,1,1)="1","Ativo",IF(MID(E62,1,1)="2","Passivo","Resultado")) -> Ativo | D62: =IF(MID(E62,10,3)="000","Sintetica","") -> Sintetica | E62: 1.1.5.01.0001 | F62: ICMS A RECUPERAR | G62: 1518065.1 | H62: D | I62: 36706.29 | J62: 1753.76 | K62: 1553017.6 | L62: D | M62: =IF(H62="D",G62,-G62) -> 1518065.1 | N62: =IF(L62="D",K62,-K62) -> 1553017.6
B63: jun/26 | C63: =IF(MID(E63,1,1)="1","Ativo",IF(MID(E63,1,1)="2","Passivo","Resultado")) -> Ativo | D63: =IF(MID(E63,10,3)="000","Sintetica","") -> Sintetica | E63: 1.1.5.01.0002 | F63: ICMS - ST A RECUPERAR | G63: 117388.41 | H63: D | I63: 0 | J63: 0 | K63: 117388.41 | L63: D | M63: =IF(H63="D",G63,-G63) -> 117388.41 | N63: =IF(L63="D",K63,-K63) -> 117388.41
B64: jun/26 | D64: =IF(MID(E64,10,3)="000","Sintetica","") -> Sintetica | E64: 1.1.5.01.0003 | F64: IPI A RECUPERAR | G64: 467418.06 | H64: D | I64: 1352.23 | J64: 0 | K64: 468770.29 | L64: D | M64: =IF(H64="D",G64,-G64) -> 467418.06 | N64: =IF(L64="D",K64,-K64) -> 468770.29
B65: jun/26 | D65: =IF(MID(E65,10,3)="000","Sintetica","") -> Sintetica | E65: 1.1.5.01.0004 | F65: PIS A RECUPERAR | G65: 25628.93 | H65: D | I65: 3346.62 | J65: 131.82 | K65: 28843.73 | L65: D | M65: =IF(H65="D",G65,-G65) -> 25628.93 | N65: =IF(L65="D",K65,-K65) -> 28843.73
B66: jun/26 | C66: =IF(MID(E66,1,1)="1","Ativo",IF(MID(E66,1,1)="2","Passivo","Resultado")) -> Ativo | D66: =IF(MID(E66,10,3)="000","Sintetica","") -> Sintetica | E66: 1.1.5.01.0005 | F66: COFINS A RECUPERAR | G66: 1535037.9 | H66: D | I66: 15417.74 | J66: 607.18 | K66: 1549848.4 | L66: D | M66: =IF(H66="D",G66,-G66) -> 1535037.9 | N66: =IF(L66="D",K66,-K66) -> 1549848.4
B67: jun/26 | C67: =IF(MID(E67,1,1)="1","Ativo",IF(MID(E67,1,1)="2","Passivo","Resultado")) -> Ativo | D67: =IF(MID(E67,10,3)="000","Sintetica","") | E67: 1.1.5.01.0010 | F67: INSS A RECUPERAR | G67: 533069.74 | H67: D | I67: 45292.44 | J67: 8908.04 | K67: 569454.14 | L67: D | M67: =IF(H67="D",G67,-G67) -> 533069.74 | N67: =IF(L67="D",K67,-K67) -> 569454.14
B68: jun/26 | C68: =IF(MID(E68,1,1)="1","Ativo",IF(MID(E68,1,1)="2","Passivo","Resultado")) -> Ativo | D68: =IF(MID(E68,10,3)="000","Sintetica","") | E68: 1.1.5.01.0011 | F68: IR S/ APLICACOES FINANCEIRAS | G68: 46009.21 | H68: D | I68: 0 | J68: 0 | K68: 46009.21 | L68: D | M68: =IF(H68="D",G68,-G68) -> 46009.21 | N68: =IF(L68="D",K68,-K68) -> 46009.21
B69: jun/26 | C69: =IF(MID(E69,1,1)="1","Ativo",IF(MID(E69,1,1)="2","Passivo","Resultado")) -> Ativo | D69: =IF(MID(E69,10,3)="000","Sintetica","") | E69: 1.1.5.01.0014 | F69: ICMS PAGO A MAIOR RECUPERAR | G69: 144281.5 | H69: D | I69: 0 | J69: 0 | K69: 144281.5 | L69: D | M69: =IF(H69="D",G69,-G69) -> 144281.5 | N69: =IF(L69="D",K69,-K69) -> 144281.5
B70: jun/26 | C70: =IF(MID(E70,1,1)="1","Ativo",IF(MID(E70,1,1)="2","Passivo","Resultado")) -> Ativo | D70: =IF(MID(E70,10,3)="000","Sintetica","") | E70: 1.1.5.01.0016 | F70: ISS PAGO A RECUPERAR | G70: 4884.24 | H70: D | I70: 0 | J70: 0 | K70: 4884.24 | L70: D | M70: =IF(H70="D",G70,-G70) -> 4884.24 | N70: =IF(L70="D",K70,-K70) -> 4884.24
B71: jun/26 | D71: =IF(MID(E71,10,3)="000","Sintetica","") -> Sintetica | E71: 1.1.7.00.0000 | F71: DESPESAS A APROPRIAR | G71: 357832.5 | H71: D | I71: 209.36 | J71: 16999.58 | K71: 341042.28 | L71: D | M71: =IF(H71="D",G71,-G71) -> 357832.5 | N71: =IF(L71="D",K71,-K71) -> 341042.28
B72: jun/26 | D72: =IF(MID(E72,10,3)="000","Sintetica","") -> Sintetica | E72: 1.1.7.01.0000 | F72: DESPESAS DO EXERCICIO SEGUINTE | G72: 357832.5 | H72: D | I72: 209.36 | J72: 16999.58 | K72: 341042.28 | L72: D | M72: =IF(H72="D",G72,-G72) -> 357832.5 | N72: =IF(L72="D",K72,-K72) -> 341042.28
B73: jun/26 | C73: =IF(MID(E73,1,1)="1","Ativo",IF(MID(E73,1,1)="2","Passivo","Resultado")) -> Ativo | D73: =IF(MID(E73,10,3)="000","Sintetica","") -> Sintetica | E73: 1.1.7.01.0002 | F73: DESPESAS ANTECIPADAS A APROPRIAR | G73: 13165.4 | H73: D | I73: 209.36 | J73: 2124.97 | K73: 11249.79 | L73: D | M73: =IF(H73="D",G73,-G73) -> 13165.4 | N73: =IF(L73="D",K73,-K73) -> 11249.79
B74: jun/26 | C74: =IF(MID(E74,1,1)="1","Ativo",IF(MID(E74,1,1)="2","Passivo","Resultado")) -> Ativo | D74: =IF(MID(E74,10,3)="000","Sintetica","") -> Sintetica | E74: 1.1.7.01.0006 | F74: VALE TRANSPORTE A APROPRIAR | G74: 32043.05 | H74: D | I74: 0 | J74: 0 | K74: 32043.05 | L74: D | M74: =IF(H74="D",G74,-G74) -> 32043.05 | N74: =IF(L74="D",K74,-K74) -> 32043.05
B75: jun/26 | C75: =IF(MID(E75,1,1)="1","Ativo",IF(MID(E75,1,1)="2","Passivo","Resultado")) -> Ativo | D75: =IF(MID(E75,10,3)="000","Sintetica","") -> Sintetica | E75: 1.1.7.01.0007 | F75: VALE ALIMENTACAO A APROPRIAR | G75: 399142.36 | H75: D | I75: 0 | J75: 0 | K75: 399142.36 | L75: D | M75: =IF(H75="D",G75,-G75) -> 399142.36 | N75: =IF(L75="D",K75,-K75) -> 399142.36
B76: jun/26 | C76: =IF(MID(E76,1,1)="1","Ativo",IF(MID(E76,1,1)="2","Passivo","Resultado")) -> Ativo | D76: =IF(MID(E76,10,3)="000","Sintetica","") -> Sintetica | E76: 1.1.7.01.0008 | F76: VALE REFEICAO A APROPRIAR | G76: 93448.93 | H76: D | I76: 0 | J76: 0 | K76: 93448.93 | L76: D | M76: =IF(H76="D",G76,-G76) -> 93448.93 | N76: =IF(L76="D",K76,-K76) -> 93448.93
B77: jun/26 | C77: =IF(MID(E77,1,1)="1","Ativo",IF(MID(E77,1,1)="2","Passivo","Resultado")) -> Ativo | D77: =IF(MID(E77,10,3)="000","Sintetica","") -> Sintetica | E77: 1.1.7.01.0009 | F77: ASSISTENCIA MEDICA A APROPRIAR | G77: 174236.68 | H77: C | I77: 0 | J77: 14030.86 | K77: 188267.54 | L77: C | M77: =IF(H77="D",G77,-G77) -> -174236.68 | N77: =IF(L77="D",K77,-K77) -> -188267.54
B78: jun/26 | D78: =IF(MID(E78,10,3)="000","Sintetica","") | E78: 1.1.7.01.0010 | F78: ASSISTENCIA ODONTO A APROPRIAR | G78: 347.19 | H78: D | I78: 0 | J78: 0 | K78: 347.19 | L78: D | M78: =IF(H78="D",G78,-G78) -> 347.19 | N78: =IF(L78="D",K78,-K78) -> 347.19
B79: jun/26 | C79: =IF(MID(E79,1,1)="1","Ativo",IF(MID(E79,1,1)="2","Passivo","Resultado")) -> Ativo | D79: =IF(MID(E79,10,3)="000","Sintetica","") | E79: 1.1.7.01.0011 | F79: VALE FARMACIA A APROPRIAR | G79: 6077.75 | H79: C | I79: 0 | J79: 843.75 | K79: 6921.5 | L79: C | M79: =IF(H79="D",G79,-G79) -> -6077.75 | N79: =IF(L79="D",K79,-K79) -> -6921.5
B80: jun/26 | C80: =IF(MID(E80,1,1)="1","Ativo",IF(MID(E80,1,1)="2","Passivo","Resultado")) -> Ativo | D80: =IF(MID(E80,10,3)="000","Sintetica","") -> Sintetica | E80: 1.2.0.00.0000 | F80: ATIVO NAO CIRCULANTE | G80: 2039953.7 | H80: D | I80: 22615 | J80: 54857.02 | K80: 2007711.6 | L80: D | M80: =IF(H80="D",G80,-G80) -> 2039953.7 | N80: =IF(L80="D",K80,-K80) -> 2007711.6
B81: jun/26 | D81: =IF(MID(E81,10,3)="000","Sintetica","") -> Sintetica | E81: 1.2.1.00.0000 | F81: REALIZAVEL A LONGO PRAZO | G81: 153703.68 | H81: D | I81: 0 | J81: 0 | K81: 153703.68 | L81: D | M81: =IF(H81="D",G81,-G81) -> 153703.68 | N81: =IF(L81="D",K81,-K81) -> 153703.68
B82: jun/26 | C82: =IF(MID(E82,1,1)="1","Ativo",IF(MID(E82,1,1)="2","Passivo","Resultado")) -> Ativo | D82: =IF(MID(E82,10,3)="000","Sintetica","") -> Sintetica | E82: 1.2.1.04.0000 | F82: DEPOSITOS JUDICIAIS | G82: 83951.85 | H82: D | I82: 0 | J82: 0 | K82: 83951.85 | L82: D | M82: =IF(H82="D",G82,-G82) -> 83951.85 | N82: =IF(L82="D",K82,-K82) -> 83951.85
B83: jun/26 | C83: =IF(MID(E83,1,1)="1","Ativo",IF(MID(E83,1,1)="2","Passivo","Resultado")) -> Ativo | D83: =IF(MID(E83,10,3)="000","Sintetica","") -> Sintetica | E83: 1.2.1.04.0001 | F83: DEPOSITOS JUDICIAIS TRABALHISTAS | G83: 83951.85 | H83: D | I83: 0 | J83: 0 | K83: 83951.85 | L83: D | M83: =IF(H83="D",G83,-G83) -> 83951.85 | N83: =IF(L83="D",K83,-K83) -> 83951.85
B84: jun/26 | C84: =IF(MID(E84,1,1)="1","Ativo",IF(MID(E84,1,1)="2","Passivo","Resultado")) -> Ativo | D84: =IF(MID(E84,10,3)="000","Sintetica","") -> Sintetica | E84: 1.2.1.06.0000 | F84: CLIENTES LONGO PRAZO | G84: 69751.83 | H84: D | I84: 0 | J84: 0 | K84: 69751.83 | L84: D | M84: =IF(H84="D",G84,-G84) -> 69751.83 | N84: =IF(L84="D",K84,-K84) -> 69751.83
B85: jun/26 | D85: =IF(MID(E85,10,3)="000","Sintetica","") -> Sintetica | E85: 1.2.1.06.0001 | F85: RETENÇAO CONTRATUAL | G85: 69751.83 | H85: D | I85: 0 | J85: 0 | K85: 69751.83 | L85: D | M85: =IF(H85="D",G85,-G85) -> 69751.83 | N85: =IF(L85="D",K85,-K85) -> 69751.83
B86: jun/26 | C86: =IF(MID(E86,1,1)="1","Ativo",IF(MID(E86,1,1)="2","Passivo","Resultado")) -> Ativo | D86: =IF(MID(E86,10,3)="000","Sintetica","") -> Sintetica | E86: 1.2.2.00.0000 | F86: INVESTIMENTOS IMOBILIZADOS INTANGIVEIS | G86: 1718276.5 | H86: D | I86: 22615 | J86: 54857.02 | K86: 1686034.5 | L86: D | M86: =IF(H86="D",G86,-G86) -> 1718276.5 | N86: =IF(L86="D",K86,-K86) -> 1686034.5
B87: jun/26 | C87: =IF(MID(E87,1,1)="1","Ativo",IF(MID(E87,1,1)="2","Passivo","Resultado")) -> Ativo | D87: =IF(MID(E87,10,3)="000","Sintetica","") -> Sintetica | E87: 1.2.2.01.0000 | F87: BENS IMOVEIS | G87: 407582.5 | H87: D | I87: 22615 | J87: 0 | K87: 430197.5 | L87: D | M87: =IF(H87="D",G87,-G87) -> 407582.5 | N87: =IF(L87="D",K87,-K87) -> 430197.5
B88: jun/26 | D88: =IF(MID(E88,10,3)="000","Sintetica","") -> Sintetica | E88: 1.2.2.01.0003 | F88: BENFEITORIAS EM IMOVEIS DE TERCEIROS | G88: 407582.5 | H88: D | I88: 22615 | J88: 0 | K88: 430197.5 | L88: D | M88: =IF(H88="D",G88,-G88) -> 407582.5 | N88: =IF(L88="D",K88,-K88) -> 430197.5
B89: jun/26 | D89: =IF(MID(E89,10,3)="000","Sintetica","") -> Sintetica | E89: 1.2.2.02.0000 | F89: INSTALACOES ADMINISTRATIVAS | G89: 735121.93 | H89: D | I89: 0 | J89: 0 | K89: 735121.93 | L89: D | M89: =IF(H89="D",G89,-G89) -> 735121.93 | N89: =IF(L89="D",K89,-K89) -> 735121.93
B90: jun/26 | C90: =IF(MID(E90,1,1)="1","Ativo",IF(MID(E90,1,1)="2","Passivo","Resultado")) -> Ativo | D90: =IF(MID(E90,10,3)="000","Sintetica","") -> Sintetica | E90: 1.2.2.02.0001 | F90: EQUIPAMENTOS DE INFORMATICA | G90: 179725.34 | H90: D | I90: 0 | J90: 0 | K90: 179725.34 | L90: D | M90: =IF(H90="D",G90,-G90) -> 179725.34 | N90: =IF(L90="D",K90,-K90) -> 179725.34
B91: jun/26 | C91: =IF(MID(E91,1,1)="1","Ativo",IF(MID(E91,1,1)="2","Passivo","Resultado")) -> Ativo | D91: =IF(MID(E91,10,3)="000","Sintetica","") -> Sintetica | E91: 1.2.2.02.0003 | F91: MOVEIS E UTENSILIOS | G91: 190926.39 | H91: D | I91: 0 | J91: 0 | K91: 190926.39 | L91: D | M91: =IF(H91="D",G91,-G91) -> 190926.39 | N91: =IF(L91="D",K91,-K91) -> 190926.39
B92: jun/26 | C92: =IF(MID(E92,1,1)="1","Ativo",IF(MID(E92,1,1)="2","Passivo","Resultado")) -> Ativo | D92: =IF(MID(E92,10,3)="000","Sintetica","") -> Sintetica | E92: 1.2.2.02.0005 | F92: INSTALACOES DIVERSAS | G92: 158626.59 | H92: D | I92: 0 | J92: 0 | K92: 158626.59 | L92: D | M92: =IF(H92="D",G92,-G92) -> 158626.59 | N92: =IF(L92="D",K92,-K92) -> 158626.59
B93: jun/26 | D93: =IF(MID(E93,10,3)="000","Sintetica","") -> Sintetica | E93: 1.2.2.02.0006 | F93: FERRAMENTAS | G93: 205843.61 | H93: D | I93: 0 | J93: 0 | K93: 205843.61 | L93: D | M93: =IF(H93="D",G93,-G93) -> 205843.61 | N93: =IF(L93="D",K93,-K93) -> 205843.61
B94: jun/26 | D94: =IF(MID(E94,10,3)="000","Sintetica","") -> Sintetica | E94: 1.2.2.03.0000 | F94: INSTALACOES INDUSTRIAIS | G94: 691395.54 | H94: D | I94: 0 | J94: 0 | K94: 691395.54 | L94: D | M94: =IF(H94="D",G94,-G94) -> 691395.54 | N94: =IF(L94="D",K94,-K94) -> 691395.54
B95: jun/26 | D95: =IF(MID(E95,10,3)="000","Sintetica","") -> Sintetica | E95: 1.2.2.03.0001 | F95: MAQUINAS E EQUIPAMENTOS | G95: 551591.21 | H95: D | I95: 0 | J95: 0 | K95: 551591.21 | L95: D | M95: =IF(H95="D",G95,-G95) -> 551591.21 | N95: =IF(L95="D",K95,-K95) -> 551591.21
B96: jun/26 | C96: =IF(MID(E96,1,1)="1","Ativo",IF(MID(E96,1,1)="2","Passivo","Resultado")) -> Ativo | D96: =IF(MID(E96,10,3)="000","Sintetica","") -> Sintetica | E96: 1.2.2.03.0002 | F96: MOVEIS E UTENSILIOS INDUSTRIAIS | G96: 139804.33 | H96: D | I96: 0 | J96: 0 | K96: 139804.33 | L96: D | M96: =IF(H96="D",G96,-G96) -> 139804.33 | N96: =IF(L96="D",K96,-K96) -> 139804.33
B97: jun/26 | C97: =IF(MID(E97,1,1)="1","Ativo",IF(MID(E97,1,1)="2","Passivo","Resultado")) -> Ativo | D97: =IF(MID(E97,10,3)="000","Sintetica","") -> Sintetica | E97: 1.2.2.05.0000 | F97: INVESTIMENTOS | G97: 24098.4 | H97: D | I97: 0 | J97: 0 | K97: 24098.4 | L97: D | M97: =IF(H97="D",G97,-G97) -> 24098.4 | N97: =IF(L97="D",K97,-K97) -> 24098.4
B98: jun/26 | D98: =IF(MID(E98,10,3)="000","Sintetica","") -> Sintetica | E98: 1.2.2.05.0001 | F98: BB CONSÓRCIOS | G98: 24098.4 | H98: D | I98: 0 | J98: 0 | K98: 24098.4 | L98: D | M98: =IF(H98="D",G98,-G98) -> 24098.4 | N98: =IF(L98="D",K98,-K98) -> 24098.4
B99: jun/26 | C99: =IF(MID(E99,1,1)="1","Ativo",IF(MID(E99,1,1)="2","Passivo","Resultado")) -> Ativo | D99: =IF(MID(E99,10,3)="000","Sintetica","") -> Sintetica | E99: 1.2.2.10.0000 | F99: DEPRECIACOES ACUMULADAS | G99: 684105.89 | H99: C | I99: 0 | J99: 43308.38 | K99: 727414.27 | L99: C | M99: =IF(H99="D",G99,-G99) -> -684105.89 | N99: =IF(L99="D",K99,-K99) -> -727414.27
B100: jun/26 | C100: =IF(MID(E100,1,1)="1","Ativo",IF(MID(E100,1,1)="2","Passivo","Resultado")) -> Ativo | D100: =IF(MID(E100,10,3)="000","Sintetica","") -> Sintetica | E100: 1.2.2.10.0003 | F100: (-) DEP ACUM - BENF IMOVEIS TERCEIROS | G100: 83310.71 | H100: C | I100: 0 | J100: 25479.12 | K100: 108789.83 | L100: C | M100: =IF(H100="D",G100,-G100) -> -83310.71 | N100: =IF(L100="D",K100,-K100) -> -108789.83
B101: jun/26 | C101: =IF(MID(E101,1,1)="1","Ativo",IF(MID(E101,1,1)="2","Passivo","Resultado")) -> Ativo | D101: =IF(MID(E101,10,3)="000","Sintetica","") -> Sintetica | E101: 1.2.2.10.0004 | F101: (-) DEP ACUM - EQUIP INFOR - INST ADM | G101: 53251.74 | H101: C | I101: 0 | J101: 3788.6 | K101: 57040.34 | L101: C | M101: =IF(H101="D",G101,-G101) -> -53251.74 | N101: =IF(L101="D",K101,-K101) -> -57040.34
...

Sheet 01.Razão
M5: =SUBTOTAL(9,M7:M120) -> -280060
B6: Período | C6: Conta | D6: Conta + Descrição | E6: Data | F6: LOTE/SUB/DOC/LINHA | G6: HISTORICO | H6: C/PARTIDA | I6: FL | J6: C CUSTO | K6: DEBITO | L6: CREDITO | M6: Valor | N6: Obs.
B7: 2021 | C7: 2.1.1.05.0005 | D7: 2.1.1.05.0005 - PROVISAO BONUS A PAGAR | E7: 44227 | F7: 000001001000014001 | G7: PROV BONUS A PAGAR ACIONISTA | H7: 4.1.1.01.0026 | I7: 0301 | K7: 0 | L7: 22500 | M7: =K7-L7 -> -22500 | N7: Efeito zero
B8: 2021 | C8: =MID(D8,1,12) -> 2.1.1.05.000 | D8: 2.1.1.05.0005 - PROVISAO BONUS A PAGAR | E8: 44255 | F8: 000001001000001001 | G8: PROV BONUS A PAGAR ACIONISTA | H8: 4.1.1.01.0026 | I8: 0301 | K8: 0 | L8: 22500 | M8: =K8-L8 -> -22500 | N8: Efeito zero
B9: 2021 | C9: =MID(D9,1,12) -> 2.1.1.05.000 | D9: 2.1.1.05.0005 - PROVISAO BONUS A PAGAR | E9: 44286 | F9: 000001001000014001 | G9: PROV BONUS A PAGAR ACIONISTA | H9: 4.1.1.01.0026 | I9: 0301 | K9: 0 | L9: 22500 | M9: =K9-L9 -> -22500 | N9: Efeito zero
B10: 2021 | C10: =MID(D10,1,12) -> 2.1.1.05.000 | D10: 2.1.1.05.0005 - PROVISAO BONUS A PAGAR | E10: 44316 | F10: 000001001000012001 | G10: PROVISAO DE BONUS MES MARÇO E ABRIL | H10: 4.1.1.01.0026 | I10: 0301 | K10: 0 | L10: 40500 | M10: =K10-L10 -> -40500 | N10: Efeito zero
B11: 2021 | C11: =MID(D11,1,12) -> 2.1.1.05.000 | D11: 2.1.1.05.0005 - PROVISAO BONUS A PAGAR | E11: 44347 | F11: 001010001000001001 | G11: PROVISAO DE BONUS MES MAIO-21 | H11: 4.1.1.01.0026 | I11: 0301 | K11: 0 | L11: 27000 | M11: =K11-L11 -> -27000 | N11: Efeito zero
B12: 2021 | C12: =MID(D12,1,12) -> 2.1.1.05.000 | D12: 2.1.1.05.0005 - PROVISAO BONUS A PAGAR | E12: 44377 | F12: 000001001000001005 | G12: PROVISAO DE BONUS JUN 2021 | H12: 4.1.1.01.0026 | I12: 0301 | K12: 0 | L12: 27000 | M12: =K12-L12 -> -27000 | N12: Efeito zero
B13: 2021 | C13: =MID(D13,1,12) -> 2.1.1.05.000 | D13: 2.1.1.05.0005 - PROVISAO BONUS A PAGAR | E13: 44407 | F13: 000001001000008001 | G13: PROV PROVISAO DE BONUS | H13: 4.1.1.01.0026 | I13: 0301 | K13: 0 | L13: 27000 | M13: =K13-L13 -> -27000 | N13: Efeito zero
B14: 2021 | C14: =MID(D14,1,12) -> 2.1.1.05.000 | D14: 2.1.1.05.0005 - PROVISAO BONUS A PAGAR | E14: 44439 | F14: 000001001000001001 | G14: PROV PROVISAO DE BONUS | H14: 4.1.1.01.0026 | I14: 0301 | K14: 0 | L14: 27000 | M14: =K14-L14 -> -27000 | N14: Efeito zero
B15: 2021 | C15: =MID(D15,1,12) -> 2.1.1.05.000 | D15: 2.1.1.05.0005 - PROVISAO BONUS A PAGAR | E15: 44467 | F15: 000001001000005001 | G15: PROV PROVISAO DE BONUS | H15: 4.1.1.01.0026 | I15: 0301 | K15: 0 | L15: 27000 | M15: =K15-L15 -> -27000 | N15: Efeito zero
B16: 2021 | C16: =MID(D16,1,12) -> 2.1.1.05.000 | D16: 2.1.1.05.0005 - PROVISAO BONUS A PAGAR | E16: 44498 | F16: 000001001000002001 | G16: PROV PROVISAO DE BONUS | H16: 4.1.1.01.0026 | I16: 0301 | K16: 0 | L16: 27000 | M16: =K16-L16 -> -27000 | N16: Efeito zero
B17: 2021 | C17: =MID(D17,1,12) -> 2.1.1.05.000 | D17: 2.1.1.05.0005 - PROVISAO BONUS A PAGAR | E17: 44529 | F17: 000001001000002001 | G17: PROV PROVISAO DE BONUS | H17: 4.1.1.01.0026 | I17: 0301 | K17: 0 | L17: 27000 | M17: =K17-L17 -> -27000 | N17: Efeito zero
B18: 2021 | C18: =MID(D18,1,12) -> 2.1.1.05.000 | D18: 2.1.1.05.0005 - PROVISAO BONUS A PAGAR | E18: 44560 | F18: 000001001000002001 | G18: PROV PROVISAO DE BONUS | H18: 4.1.1.01.0026 | I18: 0301 | K18: 0 | L18: 27000 | M18: =K18-L18 -> -27000 | N18: Efeito zero
B19: 2021 | C19: =MID(D19,1,12) -> 2.1.1.05.000 | D19: 2.1.1.05.0005 - PROVISAO BONUS A PAGAR | E19: 44561 | F19: 000001001000032001 | G19: EST PROV BONUS | H19: 4.1.1.01.0026 | I19: 0301 | K19: 324000 | L19: 0 | M19: =K19-L19 -> 324000 | N19: Efeito zero
... B34: 2022 | C34: =MID(D34,1,12) -> 2.1.1.05.000 | D34: 2.1.1.05.0005 - PROVISAO BONUS A PAGAR | E34: 44925 | F34: 000001001000152001 | G34: PROV EST BONUS | H34: 4.1.1.01.0026 | I34: 0301 | K34: 358279.2 | L34: 0 | M34: =K34-L34 -> 358279.2 | N34: Efeito zero
B35: 2023 | C35: =MID(D35,1,12) -> 2.1.1.05.000 | D35: 2.1.1.05.0005 - PROVISAO BONUS A PAGAR | E35: 44957 | F35: 000001001000024001 | G35: PROV BONUS | H35: 4.1.1.01.0026 | I35: 0301 | K35: 0 | L35: 66439 | M35: =K35-L35 -> -66439
B36: 2023 | C36: =MID(D36,1,12) -> 2.1.1.05.000 | D36: 2.1.1.05.0005 - PROVISAO BONUS A PAGAR | E36: 44985 | F36: 000001001000012001 | G36: PROV BONUS | H36: 4.1.1.01.0026 | I36: 0301 | K36: 0 | L36: 66439 | M36: =K36-L36 -> -66439
B37: 2023 | C37: =MID(D37,1,12) -> 2.1.1.05.000 | D37: 2.1.1.05.0005 - PROVISAO BONUS A PAGAR | E37: 45016 | F37: 000001001000005001 | G37: PROV BONUS | H37: 4.1.1.01.0026 | I37: 0301 | K37: 0 | L37: 66439 | M37: =K37-L37 -> -66439
B38: 2023 | C38: =MID(D38,1,12) -> 2.1.1.05.000 | D38: 2.1.1.05.0005 - PROVISAO BONUS A PAGAR | E38: 45016 | F38: 000001001000016001 | G38: PROV BONUS | H38: 4.1.1.01.0026 | I38: 0301 | K38: 0 | L38: 1 | M38: =K38-L38 -> -1
B39: 2023 | C39: =MID(D39,1,12) -> 2.1.1.05.000 | D39: 2.1.1.05.0005 - PROVISAO BONUS A PAGAR | E39: 45046 | F39: 000001001000016001 | G39: PROV BONUS | H39: 4.1.1.01.0026 | I39: 0301 | K39: 0 | L39: 66440 | M39: =K39-L39 -> -66440
B40: 2023 | C40: =MID(D40,1,12) -> 2.1.1.05.000 | D40: 2.1.1.05.0005 - PROVISAO BONUS A PAGAR | E40: 45077 | F40: 000001001011342001 | G40: VLR PROVISAO BONUS | H40: 4.1.1.01.0026 | I40: 0301 | K40: 0 | L40: 66439 | M40: =K40-L40 -> -66439
B41: 2023 | C41: =MID(D41,1,12) -> 2.1.1.05.000 | D41: 2.1.1.05.0005 - PROVISAO BONUS A PAGAR | E41: 45107 | F41: 000001001000007002 | G41: VLR PROVISAO BONUS | H41: 4.1.1.01.0026 | I41: 0301 | K41: 0 | L41: 7639 | M41: =K41-L41 -> -7639
B42: 2023 | C42: =MID(D42,1,12) -> 2.1.1.05.000 | D42: 2.1.1.05.0005 - PROVISAO BONUS A PAGAR | E42: 45138 | F42: 000001001000015002 | G42: VLR PROVISAO BONUS | H42: 4.1.1.01.0026 | I42: 0301 | K42: 0 | L42: 56639 | M42: =K42-L42 -> -56639
B43: 2023 | C43: =MID(D43,1,12) -> 2.1.1.05.000 | D43: 2.1.1.05.0005 - PROVISAO BONUS A PAGAR | E43: 45169 | F43: 000001001000003002 | G43: VLR PROVISAO BONUS | H43: 4.1.1.01.0026 | I43: 0301 | K43: 0 | L43: 56640 | M43: =K43-L43 -> -56640
B44: 2023 | C44: =MID(D44,1,12) -> 2.1.1.05.000 | D44: 2.1.1.05.0005 - PROVISAO BONUS A PAGAR | E44: 45199 | F44: 000001001000003002 | G44: VLR PROVISAO BONUS | H44: 4.1.1.01.0026 | I44: 0301 | K44: 0 | L44: 56639 | M44: =K44-L44 -> -56639
B45: 2023 | C45: =MID(D45,1,12) -> 2.1.1.05.000 | D45: 2.1.1.05.0005 - PROVISAO BONUS A PAGAR | E45: 45230 | F45: 000001001000005002 | G45: VLR PROVISAO BONUS | H45: 4.1.1.01.0026 | I45: 0301 | K45: 0 | L45: 56640 | M45: =K45-L45 -> -56640
B46: 2023 | C46: =MID(D46,1,12) -> 2.1.1.05.000 | D46: 2.1.1.05.0005 - PROVISAO BONUS A PAGAR | E46: 45260 | F46: 000001001000006002 | G46: VLR PROVISAO BONUS | H46: 4.1.1.01.0026 | I46: 0301 | K46: 116611 | L46: 0 | M46: =K46-L46 -> 116611
... B52: 2024 | C52: =MID(D52,1,12) -> 2.1.1.05.000 | D52: 2.1.1.05.0005 - PROVISAO BONUS A PAGAR | E52: 45566 | F52: 000001001000001001 | G52: VLR PROVISAO DE BONUS | H52: 4.1.1.01.0026 | I52: 0301 | K52: 56880 | L52: 0 | M52: =K52-L52 -> 56880
B53: 2024 | C53: =MID(D53,1,12) -> 2.1.1.05.000 | D53: 2.1.1.05.0005 - PROVISAO BONUS A PAGAR | E53: 45412 | F53: 99999B001000002001 | G53: 313 - PREMIO | H53: 4.1.1.01.0020 | I53: 0301 | J53: 0.3.5.000001 | K53: 55372.32 | L53: 0 | M53: =K53-L53 -> 55372.32
B54: 2024 | C54: =MID(D54,1,12) -> 2.1.1.05.000 | D54: 2.1.1.05.0005 - PROVISAO BONUS A PAGAR | E54: 45595 | F54: 000001001000003001 | G54: VLR EST PREVISAO BONUS | H54: 4.1.1.01.0026 | I54: 0302 | K54: 42232 | L54: 0 | M54: =K54-L54 -> 42232
B55: 2024 | C55: =MID(D55,1,12) -> 2.1.1.05.000 | D55: 2.1.1.05.0005 - PROVISAO BONUS A PAGAR | E55: 45536 | F55: 000001001000003001 | G55: VLR PROVISAO DE BONUS | H55: 4.1.1.01.0026 | I55: 0301 | K55: 40797 | L55: 0 | M55: =K55-L55 -> 40797
B56: 2024 | C56: =MID(D56,1,12) -> 2.1.1.05.000 | D56: 2.1.1.05.0005 - PROVISAO BONUS A PAGAR | E56: 45412 | F56: 000001001000007002 | G56: 313 - PRÊMIO | H56: 3.1.1.04.0020 | I56: 0302 | K56: 31263.99 | L56: 0 | M56: =K56-L56 -> 31263.99
B57: 2024 | C57: =MID(D57,1,12) -> 2.1.1.05.000 | D57: 2.1.1.05.0005 - PROVISAO BONUS A PAGAR | E57: 45412 | F57: 000001001000014004 | G57: 313 - PREMIO | H57: 4.2.1.01.0020 | I57: 0301 | K57: 27273.52 | L57: 0 | M57: =K57-L57 -> 27273.52
B58: 2024 | C58: =MID(D58,1,12) -> 2.1.1.05.000 | D58: 2.1.1.05.0005 - PROVISAO BONUS A PAGAR | E58: 45412 | F58: 000001001000014003 | G58: 313 - PREMIO | H58: 3.1.1.04.0020 | I58: 0301 | K58: 25240.72 | L58: 0 | M58: =K58-L58 -> 25240.72
B59: 2024 | C59: =MID(D59,1,12) -> 2.1.1.05.000 | D59: 2.1.1.05.0005 - PROVISAO BONUS A PAGAR | E59: 45536 | F59: 000001001000002001 | G59: VLR PROVISAO BONUS | H59: 4.1.1.01.0026 | I59: 0302 | K59: 24648 | L59: 0 | M59: =K59-L59 -> 24648
B60: 2024 | C60: =MID(D60,1,12) -> 2.1.1.05.000 | D60: 2.1.1.05.0005 - PROVISAO BONUS A PAGAR | E60: 45412 | F60: 000001001000007005 | G60: 313 - PRÊMIO | H60: 3.1.1.02.0020 | I60: 0302 | J60: 0.1.1.000001 | K60: 24529.8 | L60: 0 | M60: =K60-L60 -> 24529.8
B61: 2024 | C61: =MID(D61,1,12) -> 2.1.1.05.000 | D61: 2.1.1.05.0005 - PROVISAO BONUS A PAGAR | E61: 45412 | F61: 000001001000014001 | G61: 313 - PREMIO | H61: 4.2.1.01.0020 | I61: 0301 | J61: 0.3.7.000002 | K61: 23427.51 | L61: 0 | M61: =K61-L61 -> 23427.51
B62: 2024 | C62: =MID(D62,1,12) -> 2.1.1.05.000 | D62: 2.1.1.05.0005 - PROVISAO BONUS A PAGAR | E62: 45412 | F62: 000001001000007004 | G62: 313 - PRÊMIO | H62: 3.1.1.04.0020 | I62: 0302 | K62: 22791.79 | L62: 0 | M62: =K62-L62 -> 22791.79
B63: 2024 | C63: =MID(D63,1,12) -> 2.1.1.05.000 | D63: 2.1.1.05.0005 - PROVISAO BONUS A PAGAR | E63: 45412 | F63: 000001001000014002 | G63: 313 - PREMIO | H63: 4.1.1.01.0020 | I63: 0301 | K63: 21166.53 | L63: 0 | M63: =K63-L63 -> 21166.53
B64: 2024 | C64: =MID(D64,1,12) -> 2.1.1.05.000 | D64: 2.1.1.05.0005 - PROVISAO BONUS A PAGAR | E64: 45412 | F64: 000001001000007006 | G64: 313 - PRÊMIO | H64: 4.2.1.01.0020 | I64: 0302 | J64: 0.3.5.000004 | K64: 18052.65 | L64: 0 | M64: =K64-L64 -> 18052.65
B65: 2024 | C65: =MID(D65,1,12) -> 2.1.1.05.000 | D65: 2.1.1.05.0005 - PROVISAO BONUS A PAGAR | E65: 45412 | F65: 000001001000010001 | G65: VLR PROVISAO BONUS REF 2023 | H65: 4.1.1.01.0026 | I65: 0302 | J65: 0.3.8.000001 | K65: 0 | L65: 207091 | M65: =K65-L65 -> -207091 | N65: Efeito zero
B66: 2024 | C66: =MID(D66,1,12) -> 2.1.1.05.000 | D66: 2.1.1.05.0005 - PROVISAO BONUS A PAGAR | E66: 45412 | F66: 000001001000007003 | G66: 313 - PRÊMIO | H66: 3.1.1.04.0020 | I66: 0302 | K66: 13393.18 | L66: 0 | M66: =K66-L66 -> 13393.18
B67: 2024 | C67: =MID(D67,1,12) -> 2.1.1.05.000 | D67: 2.1.1.05.0005 - PROVISAO BONUS A PAGAR | E67: 45412 | F67: 000001001000012001 | G67: VLR AJUSTE PROVISAO FILIAL | H67: 4.1.1.01.0026 | I67: 0301 | J67: 0.3.8.000018 | K67: 639.42 | L67: 0 | M67: =K67-L67 -> 639.42
B68: 2024 | C68: =MID(D68,1,12) -> 2.1.1.05.000 | D68: 2.1.1.05.0005 - PROVISAO BONUS A PAGAR | E68: 45412 | F68: 000001001000009001 | G68: VLR AJUSTE PROVISAO FILIAL | H68: 4.1.1.01.0026 | I68: 0302 | J68: 0.3.7.000007 | K68: 0 | L68: 639.42 | M68: =K68-L68 -> -639.42
B69: 2024 | C69: =MID(D69,1,12) -> 2.1.1.05.000 | D69: 2.1.1.05.0005 - PROVISAO BONUS A PAGAR | E69: 45626 | F69: 000001001000002002 | G69: VLR PROVISAO DE BONUS | H69: 4.1.1.01.0026 | I69: 0301 | K69: 0 | L69: 10257 | M69: =K69-L69 -> -10257
B70: 2024 | C70: =MID(D70,1,12) -> 2.1.1.05.000 | D70: 2.1.1.05.0005 - PROVISAO BONUS A PAGAR | E70: 45657 | F70: 99999L001000001001 | G70: PROVISÃO BONUS | H70: 4.1.1.01.0026 | I70: 0301 | K70: 0 | L70: 10257 | M70: =K70-L70 -> -10257
B71: 2024 | C71: =MID(D71,1,12) -> 2.1.1.05.000 | D71: 2.1.1.05.0005 - PROVISAO BONUS A PAGAR | E71: 45566 | F71: 000001001000001002 | G71: VLR PROVISAO DE BONUS | H71: 4.1.1.01.0026 | I71: 0301 | K71: 0 | L71: 11967 | M71: =K71-L71 -> -11967
B72: 2024 | C72: =MID(D72,1,12) -> 2.1.1.05.000 | D72: 2.1.1.05.0005 - PROVISAO BONUS A PAGAR | E72: 45412 | F72: 000001001000016001 | G72: VLR PROVISAO BONUS 2023 | H72: 4.1.1.01.0026 | I72: 0301 | J72: 0.3.4.000001 | K72: 207091 | L72: 0 | M72: =K72-L72 -> 207091 | N72: Efeito zero
B73: 2024 | C73: =MID(D73,1,12) -> 2.1.1.05.000 | D73: 2.1.1.05.0005 - PROVISAO BONUS A PAGAR | E73: 45626 | F73: 000001001000001001 | G73: VLR PREVISAO BONUS | H73: 4.1.1.01.0026 | I73: 0302 | K73: 0 | L73: 12740 | M73: =K73-L73 -> -12740
B74: 2024 | C74: =MID(D74,1,12) -> 2.1.1.05.000 | D74: 2.1.1.05.0005 - PROVISAO BONUS A PAGAR | E74: 45657 | F74: 000001001000008001 | G74: VLR PREVISAO BONUS | H74: 4.1.1.01.0026 | I74: 0302 | K74: 0 | L74: 12740 | M74: =K74-L74 -> -12740
B75: 2024 | C75: =MID(D75,1,12) -> 2.1.1.05.000 | D75: 2.1.1.05.0005 - PROVISAO BONUS A PAGAR | E75: 45412 | F75: 000001001000015001 | G75: VLR PROV BONUS REF 2023 | H75: 4.1.1.01.0026 | I75: 0301 | J75: 0.3.3.000004 | K75: 0 | L75: 17988.02 | M75: =K75-L75 -> -17988.02
B76: 2024 | C76: =MID(D76,1,12) -> 2.1.1.05.000 | D76: 2.1.1.05.0005 - PROVISAO BONUS A PAGAR | E76: 45535 | F76: 000001001000001001 | G76: VLR PROVISAO BONUS | H76: 4.1.1.01.0026 | I76: 0302 | K76: 0 | L76: 28076 | M76: =K76-L76 -> -28076
B77: 2024 | C77: =MID(D77,1,12) -> 2.1.1.05.000 | D77: 2.1.1.05.0005 - PROVISAO BONUS A PAGAR | E77: 45322 | F77: 000001001000004001 | G77: VLR PROVISAO DE BONUS | H77: 4.1.1.01.0026 | I77: 0301 | K77: 0 | L77: 39273 | M77: =K77-L77 -> -39273
B78: 2024 | C78: =MID(D78,1,12) -> 2.1.1.05.000 | D78: 2.1.1.05.0005 - PROVISAO BONUS A PAGAR | E78: 45352 | F78: 000001001000003001 | G78: VLR PROVISAO DE BONUS | H78: 4.1.1.01.0026 | I78: 0301 | K78: 0 | L78: 46472 | M78: =K78-L78 -> -46472
B79: 2024 | C79: =MID(D79,1,12) -> 2.1.1.05.000 | D79: 2.1.1.05.0005 - PROVISAO BONUS A PAGAR | E79: 45535 | F79: 000001001000004001 | G79: VLR PROVISAO DE BONUS | H79: 4.1.1.01.0026 | I79: 0301 | K79: 0 | L79: 46472 | M79: =K79-L79 -> -46472
B80: 2024 | C80: =MID(D80,1,12) -> 2.1.1.05.000 | D80: 2.1.1.05.0005 - PROVISAO BONUS A PAGAR | E80: 45382 | F80: 000001001000011001 | G80: VLR PROVISAO DE BONUS | H80: 4.1.1.01.0026 | I80: 0301 | K80: 0 | L80: 46473 | M80: =K80-L80 -> -46473
B81: 2024 | C81: =MID(D81,1,12) -> 2.1.1.05.000 | D81: 2.1.1.05.0005 - PROVISAO BONUS A PAGAR | E81: 45412 | F81: 000001001000006001 | G81: VLR PROVISAO DE BONUS | H81: 4.1.1.01.0026 | I81: 0301 | K81: 0 | L81: 46473 | M81: =K81-L81 -> -46473
B82: 2024 | C82: =MID(D82,1,12) -> 2.1.1.05.000 | D82: 2.1.1.05.0005 - PROVISAO BONUS A PAGAR | E82: 45443 | F82: 000001001000002001 | G82: VLR PROVISAO DE BONUS | H82: 4.1.1.01.0026 | I82: 0301 | K82: 0 | L82: 46473 | M82: =K82-L82 -> -46473
B83: 2024 | C83: =MID(D83,1,12) -> 2.1.1.05.000 | D83: 2.1.1.05.0005 - PROVISAO BONUS A PAGAR | E83: 45473 | F83: 000001001000002001 | G83: VLR PROVISAO DE BONUS | H83: 4.1.1.01.0026 | I83: 0301 | K83: 0 | L83: 46473 | M83: =K83-L83 -> -46473
B84: 2024 | C84: =MID(D84,1,12) -> 2.1.1.05.000 | D84: 2.1.1.05.0005 - PROVISAO BONUS A PAGAR | E84: 45504 | F84: 000001001000002001 | G84: VLR PROVISAO DE BONUS | H84: 4.1.1.01.0026 | I84: 0301 | K84: 0 | L84: 46473 | M84: =K84-L84 -> -46473
B85: 2024 | C85: =MID(D85,1,12) -> 2.1.1.05.000 | D85: 2.1.1.05.0005 - PROVISAO BONUS A PAGAR | E85: 45565 | F85: 000001001000003001 | G85: VLR PROVISAO BONUS | H85: 4.1.1.01.0026 | I85: 0302 | K85: 0 | L85: 48811 | M85: =K85-L85 -> -48811
B86: 2024 | C86: =MID(D86,1,12) -> 2.1.1.05.000 | D86: 2.1.1.05.0005 - PROVISAO BONUS A PAGAR | E86: 45382 | F86: 000001001000002001 | G86: VLR PROVISAO BONUS | H86: 4.1.1.01.0026 | I86: 0302 | K86: 0 | L86: 51772 | M86: =K86-L86 -> -51772
B87: 2024 | C87: =MID(D87,1,12) -> 2.1.1.05.000 | D87: 2.1.1.05.0005 - PROVISAO BONUS A PAGAR | E87: 45322 | F87: 000001001000005001 | G87: VLR PROVISAO BONUS | H87: 4.1.1.01.0026 | I87: 0302 | K87: 0 | L87: 51773 | M87: =K87-L87 -> -51773
... B90: 2024 | C90: =MID(D90,1,12) -> 2.1.1.05.000 | D90: 2.1.1.05.0005 - PROVISAO BONUS A PAGAR | E90: 45443 | F90: 000001001000001001 | G90: VLR PROVISAO BONUS | H90: 4.1.1.01.0026 | I90: 0302 | K90: 0 | L90: 51773 | M90: =K90-L90 -> -51773
B91: 2024 | C91: =MID(D91,1,12) -> 2.1.1.05.000 | D91: 2.1.1.05.0005 - PROVISAO BONUS A PAGAR | E91: 45473 | F91: 000001001000001001 | G91: VLR PROVISAO BONUS | H91: 4.1.1.01.0026 | I91: 0302 | J91: 0.1.1.000001 | K91: 0 | L91: 51773 | M91: =K91-L91 -> -51773
B92: 2024 | C92: =MID(D92,1,12) -> 2.1.1.05.000 | D92: 2.1.1.05.0005 - PROVISAO BONUS A PAGAR | E92: 45504 | F92: 000001001000001001 | G92: VLR PROVISAO BONUS | H92: 4.1.1.01.0026 | I92: 0302 | K92: 0 | L92: 51773 | M92: =K92-L92 -> -51773
B93: 2024 | C93: =MID(D93,1,12) -> 2.1.1.05.000 | D93: 2.1.1.05.0005 - PROVISAO BONUS A PAGAR | E93: 45413 | F93: 99999E001000002001 | G93: RECLASS VLR PG FOL 000003388- FOLHA DEPAGAMENTO SALARIOS E ORDENADOS | H93: 2.1.1.03.0001 | I93: 0302 | J93: 0.3.7.000001 | K93: 0 | L93: 71574.93 | M93: =K93-L93 -> -71574.93
B94: 2025 | C94: =MID(D94,1,12) -> 2.1.1.05.000 | D94: 2.1.1.05.0005 - PROVISAO BONUS A PAGAR | E94: 45716 | F94: 99999L001000001001 | G94: PROVISÃO BÔNUS JAN-25 | H94: 4.1.1.01.0026 | I94: 0301 | K94: 0 | L94: 76653 | M94: =K94-L94 -> -76653
B95: 2025 | C95: =MID(D95,1,12) -> 2.1.1.05.000 | D95: 2.1.1.05.0005 - PROVISAO BONUS A PAGAR | E95: 45716 | F95: 99999L001000002001 | G95: PROVISÃO BÔNUS FEV-25 | H95: 4.1.1.01.0026 | I95: 0301 | K95: 0 | L95: 76653 | M95: =K95-L95 -> -76653
B96: 2025 | C96: =MID(D96,1,12) -> 2.1.1.05.000 | D96: 2.1.1.05.0005 - PROVISAO BONUS A PAGAR | E96: 45747 | F96: 99999L001000001001 | G96: PROVISÃO BÔNUS MAR-25 | H96: 4.1.1.01.0026 | I96: 0301 | K96: 0 | L96: 76653 | M96: =K96-L96 -> -76653
B97: 2025 | C97: =MID(D97,1,12) -> 2.1.1.05.000 | D97: 2.1.1.05.0005 - PROVISAO BONUS A PAGAR | E97: 45747 | F97: 99999L001000002001 | G97: REVERSÃO - PROVISÃO DE BÔNUS REF. JAN-25 | H97: 4.1.1.01.0026 | I97: 0301 | K97: 76653 | L97: 0 | M97: =K97-L97 -> 76653
B98: 2025 | C98: =MID(D98,1,12) -> 2.1.1.05.000 | D98: 2.1.1.05.0005 - PROVISAO BONUS A PAGAR | E98: 45777 | F98: 000001001000002001 | G98: PROVISÃO BONUS ABRIL-2025 | H98: 4.1.1.01.0026 | I98: 0301 | K98: 0 | L98: 76653 | M98: =K98-L98 -> -76653
B99: 2025 | C99: =MID(D99,1,12) -> 2.1.1.05.000 | D99: 2.1.1.05.0005 - PROVISAO BONUS A PAGAR | E99: 45808 | F99: 000001001000005001 | G99: PROVISÃO BONUS-MAIO/25 | H99: 4.1.1.01.0026 | I99: 0301 | K99: 0 | L99: 62406 | M99: =K99-L99 -> -62406
B100: 2025 | C100: =MID(D100,1,12) -> 2.1.1.05.000 | D100: 2.1.1.05.0005 - PROVISAO BONUS A PAGAR | E100: 45809 | F100: 000001001000007001 | G100: PROVISÃO BONUS-JUN/25 | H100: 4.1.1.01.0026 | I100: 0301 | K100: 0 | L100: 1408 | M100: =K100-L100 -> -1408
B101: 2025 | C101: =MID(D101,1,12) -> 2.1.1.05.000 | D101: 2.1.1.05.0005 - PROVISAO BONUS A PAGAR | E101: 45839 | F101: 000001001000009001 | G101: REVERSÃO BONUS REF. 2024 | H101: 4.1.1.01.0026 | I101: 0301 | K101: 350000 | L101: 0 | M101: =K101-L101 -> 350000
B102: 2025 | C102: =MID(D102,1,12) -> 2.1.1.05.000 | D102: 2.1.1.05.0005 - PROVISAO BONUS A PAGAR | E102: 46021 | F102: 000001001000001001 | G102: ESTORNO PROV 2024 | H102: 4.1.1.01.0026 | I102: 0301 | K102: 225387.67 | L102: 0 | M102: =K102-L102 -> 225387.67
B103: 2026 | C103: =MID(D103,1,12) -> 2.1.1.05.000 | D103: 2.1.1.05.0005 - PROVISAO BONUS A PAGAR | E103: 46053 | F103: 000001001000003001 | G103: PROVISÃO BÔNUS JAN-2026 | H103: 4.1.1.01.0026 | I103: 0302 | K103: 0 | L103: 22757 | M103: =K103-L103 -> -22757
B104: 2026 | C104: =MID(D104,1,12) -> 2.1.1.05.000 | D104: 2.1.1.05.0005 - PROVISAO BONUS A PAGAR | E104: 46081 | F104: 000001001000002001 | G104: PROVISÃO BÔNUS FEV-2026 | H104: 4.1.1.01.0026 | I104: 0302 | K104: 0 | L104: 22757 | M104: =K104-L104 -> -22757
B105: 2026 | C105: =MID(D105,1,12) -> 2.1.1.05.000 | D105: 2.1.1.05.0005 - PROVISAO BONUS A PAGAR | E105: 46112 | F105: 000001001000005001 | G105: PROVISÃO BÔNUS MAR-2026 | H105: 4.1.1.01.0026 | I105: 0302 | K105: 0 | L105: 22757 | M105: =K105-L105 -> -22757
... B111: 2026 | C111: =MID(D111,1,12) -> 2.1.1.05.000 | D111: 2.1.1.05.0005 - PROVISAO BONUS A PAGAR | E111: 46142 | F111: WN2026001000004005 | G111: REV.VLR FOPG 313 - PREMIO | H111: 3.1.1.04.0020 | I111: 0302 | K111: 7176.11 | L111: 0 | M111: =K111-L111 -> 7176.11
B112: 2026 | C112: =MID(D112,1,12) -> 2.1.1.05.000 | D112: 2.1.1.05.0005 - PROVISAO BONUS A PAGAR | E112: 46142 | F112: WN2026001000004006 | G112: REV.VLR FOPG 313 - PREMIO | H112: 3.1.1.04.0020 | I112: 0302 | J112: 0.3.7.000007 | K112: 4427.88 | L112: 0 | M112: =K112-L112 -> 4427.88
B113: 2026 | C113: =MID(D113,1,12) -> 2.1.1.05.000 | D113: 2.1.1.05.0005 - PROVISAO BONUS A PAGAR | E113: 46173 | F113: 000001001000002001 | G113: PROVISÃO BÔNUS MAI - 2026 | H113: 4.1.1.01.0026 | I113: 0302 | J113: 0.3.2.000001 | K113: 0 | L113: 22757 | M113: =K113-L113 -> -22757
B114: 2026 | C114: =MID(D114,1,12) -> 2.1.1.05.000 | D114: 2.1.1.05.0005 - PROVISAO BONUS A PAGAR | E114: 46173 | F114: WN2026001000003003 | G114: REV.VLR FOPG 402 - DESCONTO DIVERSOS | H114: 4.4.1.01.0011 | I114: 0302 | J114: 0.3.2.000001 | K114: 0 | L114: 20828.18 | M114: =K114-L114 -> -20828.18
B115: 2026 | C115: =MID(D115,1,12) -> 2.1.1.05.000 | D115: 2.1.1.05.0005 - PROVISAO BONUS A PAGAR | E115: 46173 | F115: WN2026001000003004 | G115: REV.VLR FOPG 313 - PREMIO | H115: 4.1.1.01.0020 | I115: 0302 | J115: 0.3.2.000001 | K115: 27244.78 | L115: 0 | M115: =K115-L115 -> 27244.78
B116: 2026 | C116: =MID(D116,1,12) -> 2.1.1.05.000 | D116: 2.1.1.05.0005 - PROVISAO BONUS A PAGAR | E116: 46203 | F116: IS0000001000003001 | G116: PROVISÃO BÔNUS JUN-2026 | H116: 4.1.1.01.0026 | I116: 0302 | J116: 0.3.7.000007 | K116: 0 | L116: 22757 | M116: =K116-L116 -> -22757
B117: 2026 | C117: =MID(D117,1,12) -> 2.1.1.05.000 | D117: 2.1.1.05.0005 - PROVISAO BONUS A PAGAR | E117: 46203 | F117: WN2026001000004001 | G117: RECLAS.VLR FOPG 313 - PREMIO | H117: 3.1.1.04.0020 | I117: 0302 | J117: 0.3.8.000025 | K117: 5737.83 | L117: 0 | M117: =K117-L117 -> 5737.83
B118: 2026 | C118: =MID(D118,1,12) -> 2.1.1.05.000 | D118: 2.1.1.05.0005 - PROVISAO BONUS A PAGAR | E118: 46203 | F118: WN2026001000004002 | G118: RECLAS.VLR FOPG 313 - PREMIO | H118: 4.1.1.01.0020 | I118: 0302 | K118: 44468.54 | L118: 0 | M118: =K118-L118 -> 44468.54
B119: 2026 | C119: =MID(D119,1,12) -> 2.1.1.05.000 | D119: 2.1.1.05.0005 - PROVISAO BONUS A PAGAR | E119: 46203 | F119: WN2026001000004003 | G119: RECLAS.VLR FOPG 402 - DESCONTO DIVERSOS | H119: 4.4.1.01.0011 | I119: 0302 | J119: 0.3.2.000001 | K119: 0 | L119: 33571.79 | M119: =K119-L119 -> -33571.79
B120: 2026 | C120: =MID(D120,1,12) -> 2.1.1.05.000 | D120: 2.1.1.05.0005 - PROVISAO BONUS A PAGAR | E120: 46203 | F120: WN2026001000004004 | G120: RECLAS.VLR FOPG 402 - DESCONTO DIVERSOS | H120: 4.4.1.01.0011 | I120: 0302 | J120: 0.3.2.000001 | K120: 0 | L120: 4159.93 | M120: =K120-L120 -> -4159.93

Sheet 02.Suporte
R1: Lançamento
C4: Mês | J4: x
C5: Acumulado | E5: x | F5: x | G5: x | H5: x | I5: x | J5: x
B6: BU | C6: Provisão e BU | E6: Jan | F6: Fev | G6: Mar | H6: Abr | I6: Mai | J6: Jun | K6: Jul | L6: Ago | M6: Set | N6: Out | O6: Nov | P6: Dez | Q6: Saldo | S6: Data | T6: DB | U6: CR | V6: Valor | W6: C.C | X6: C.C | Y6: Histórico
B7: Ambar | C7: Bônus | E7: 99320 | F7: 99320 | G7: 99320 | H7: 99320 | I7: 99320 | J7: 99320 | K7: 99320 | L7: 99320 | M7: 99320 | N7: 99320 | O7: 99320 | P7: 99320 | Q7: =SUMIFS($E$7:$P$7,$E$5:$P$5,"x") -> 595920 | S7: 46203 | T7: 5.1.3.80.140 | U7: 2.1.5.10.050 | V7: =SUMIFS($E$7:$P$7,$E$4:$P$4,"x") -> 99320 | W7: 5.3.1.7 | X7: 5.3.1.7 | Y7: PROVISAO BONUS POLAR 06/2026

Sheet 03.Conciliação
B6: Período | C6: BU | D6: Classificação | E6: Valor | F6: Obs.
B7: 2023 | C7: Ambar Tech | D7: Provisão Bônus - 2023 | E7: =SUMIFS('01.Razão'!$M:$M,'01.Razão'!$N:$N,'03.Conciliação'!$D7) -> 0
B8: 2023 | C8: Ambar Tech | D8: Reversão Bônus - 2023 | E8: =SUMIFS('01.Razão'!$M:$M,'01.Razão'!$N:$N,'03.Conciliação'!$D8) -> 0
B10: 2023 | C10: Ambar Tech | D10: Saldo | E10: =SUM(E7:E8) -> 0 | F10: Saldo baixado a maior referente a provisão de Bônus - 2023
B13: 2024 | C13: Ambar Tech | D13: Provisão Bônus - 2024 | E13: =SUMIFS('01.Razão'!$M:$M,'01.Razão'!$N:$N,'03.Conciliação'!$D13) -> 0
B14: 2024 | C14: Ambar Tech | D14: Reversão Bônus - 2024 | E14: =SUMIFS('01.Razão'!$M:$M,'01.Razão'!$N:$N,'03.Conciliação'!$D14) -> 0
B16: 2024 | C16: Ambar Tech | D16: Saldo | E16: =SUM(E13:E14) -> 0 | F16: Saldo em aberto referente a Provisão de Bônus - 2024
B18: 2025 | C18: Ambar Tech | D18: Provisão Bônus - 2025 | E18: =SUMIFS('01.Razão'!$M:$M,'01.Razão'!$N:$N,'03.Conciliação'!$D18) -> 0
B19: 2025 | C19: Ambar Tech | D19: Reversão Bônus - 2025 | E19: =SUMIFS('01.Razão'!$M:$M,'01.Razão'!$N:$N,'03.Conciliação'!$D19) -> 0
B21: 2025 | C21: Ambar Tech | D21: Saldo | E21: =SUM(E18:E19) -> 0 | F21: Saldo em aberto referente a Provisão de Bônus - 2025
B23: 2026 | C23: Ambar Tech | D23: Provisão Bônus - 2026 | E23: =SUMIFS('01.Razão'!$M:$M,'01.Razão'!$N:$N,'03.Conciliação'!$D23) -> 0
B24: 2026 | C24: Ambar Tech | D24: Reversão Bônus - 2026 | E24: =SUMIFS('01.Razão'!$M:$M,'01.Razão'!$N:$N,'03.Conciliação'!$D24) -> 0
B26: 2026 | C26: Ambar Tech | D26: Saldo | E26: =SUM(E23:E24) -> 0 | F26: Saldo em aberto referente a Provisão de Bônus - 2026
B28: 2026 | C28: Ambar Tech | D28: Saldo - Passivo | E28: =SUM(E26,E21,E16,E10) -> 0
